This Class  : ru.andrew.jclazz.apps.tester.tests.ops.Test_CheckCast
Super Class : java.lang.Object
Implemented Interfaces:

Version: 46.0
JVM supported: 1.2 and greater

Access Flags: 33 ( PUBLIC  SUPER )

Attributes:
@SourceFile: Test_CheckCast.java

Fields:
k : int
{
    Access Flags: 1 ( PUBLIC )

    Attributes:
}


Methods:
<init> : () : void
{
    Access Flags: 1 ( PUBLIC )

    Attributes:
    CODE
       (
        Max stack = 1
        Max locals = 1
        Attributes:
            @LineNumberTable:
                0: line 10
                4: line 11
            @LocalVariableTable: 
                0+5: this (Lru/andrew/jclazz/apps/tester/tests/ops/Test_CheckCast;), 0
        Exceptions:
       )
    {
        0 aload_0
        1 invokespecial <init>
        4 return
    }
}

test1 : (java.util.List) : void
{
    Access Flags: 1 ( PUBLIC )

    Attributes:
    CODE
       (
        Max stack = 2
        Max locals = 3
        Attributes:
            @LineNumberTable:
                0: line 15
                11: line 16
            @LocalVariableTable: 
                0+12: this (Lru/andrew/jclazz/apps/tester/tests/ops/Test_CheckCast;), 0
                0+12: list (Ljava/util/List;), 1
                11+1: str (Ljava/lang/String;), 2
        Exceptions:
       )
    {
        0 aload_1
        1 iconst_0
        2 invokeinterface get
        7 checkcast java.lang.String
        10 astore_2
        11 return
    }
}

test2 : (java.lang.Object[]) : void
{
    Access Flags: 1 ( PUBLIC )

    Attributes:
    CODE
       (
        Max stack = 1
        Max locals = 3
        Attributes:
            @LineNumberTable:
                0: line 20
                5: line 21
            @LocalVariableTable: 
                0+6: this (Lru/andrew/jclazz/apps/tester/tests/ops/Test_CheckCast;), 0
                0+6: objs ([Ljava/lang/Object;), 1
                5+1: list ([Ljava/lang/Integer;), 2
        Exceptions:
       )
    {
        0 aload_1
        1 checkcast java.lang.Integer[]
        4 astore_2
        5 return
    }
}

test3 : (java.util.List) : void
{
    Access Flags: 1 ( PUBLIC )

    Attributes:
    CODE
       (
        Max stack = 2
        Max locals = 2
        Attributes:
            @LineNumberTable:
                0: line 25
                14: line 26
            @LocalVariableTable: 
                0+15: this (Lru/andrew/jclazz/apps/tester/tests/ops/Test_CheckCast;), 0
                0+15: list (Ljava/util/List;), 1
        Exceptions:
       )
    {
        0 aload_1
        1 iconst_0
        2 invokeinterface get
        7 checkcast java.lang.Integer
        10 invokevirtual intValue
        13 pop
        14 return
    }
}

test4 : (java.util.List) : void
{
    Access Flags: 1 ( PUBLIC )

    Attributes:
    CODE
       (
        Max stack = 2
        Max locals = 3
        Attributes:
            @LineNumberTable:
                0: line 30
                12: line 31
            @LocalVariableTable: 
                0+13: this (Lru/andrew/jclazz/apps/tester/tests/ops/Test_CheckCast;), 0
                0+13: list (Ljava/util/List;), 1
                12+1: len (I), 2
        Exceptions:
       )
    {
        0 aload_1
        1 iconst_0
        2 invokeinterface get
        7 checkcast java.lang.Object[]
        10 arraylength
        11 istore_2
        12 return
    }
}

test5 : (java.util.List) : void
{
    Access Flags: 1 ( PUBLIC )

    Attributes:
    CODE
       (
        Max stack = 2
        Max locals = 3
        Attributes:
            @LineNumberTable:
                0: line 35
                14: line 36
            @LocalVariableTable: 
                0+15: this (Lru/andrew/jclazz/apps/tester/tests/ops/Test_CheckCast;), 0
                0+15: list (Ljava/util/List;), 1
                14+1: i (I), 2
        Exceptions:
       )
    {
        0 aload_1
        1 iconst_0
        2 invokeinterface get
        7 checkcast ru.andrew.jclazz.apps.tester.tests.ops.Test_CheckCast
        10 getfield k
        13 istore_2
        14 return
    }
}

Constant Pool:
0: 
1: Methodref: java.lang.Object.<init> (()V)
2: InterfaceMethodref: java.util.List.get ((I)Ljava/lang/Object;)
3: Class: java.lang.String
4: Class: java.lang.Integer[]
5: Class: java.lang.Integer
6: Methodref: java.lang.Integer.intValue (()I)
7: Class: java.lang.Object[]
8: Class: ru.andrew.jclazz.apps.tester.tests.ops.Test_CheckCast
9: Fieldref: int
10: Class: java.lang.Object
11: Utf8: k
12: Utf8: I
13: Utf8: <init>
14: Utf8: ()V
15: Utf8: Code
16: Utf8: LineNumberTable
17: Utf8: LocalVariableTable
18: Utf8: this
19: Utf8: Lru/andrew/jclazz/apps/tester/tests/ops/Test_CheckCast;
20: Utf8: test1
21: Utf8: (Ljava/util/List;)V
22: Utf8: list
23: Utf8: Ljava/util/List;
24: Utf8: str
25: Utf8: Ljava/lang/String;
26: Utf8: test2
27: Utf8: ([Ljava/lang/Object;)V
28: Utf8: objs
29: Utf8: [Ljava/lang/Object;
30: Utf8: [Ljava/lang/Integer;
31: Utf8: test3
32: Utf8: test4
33: Utf8: len
34: Utf8: test5
35: Utf8: i
36: Utf8: SourceFile
37: Utf8: Test_CheckCast.java
38: NameAndType: <init> (()V)
39: Class: java.util.List
40: NameAndType: get ((I)Ljava/lang/Object;)
41: Utf8: java/lang/String
42: Utf8: java/lang/Integer
43: NameAndType: intValue (()I)
44: Utf8: ru/andrew/jclazz/apps/tester/tests/ops/Test_CheckCast
45: NameAndType: k (I)
46: Utf8: java/lang/Object
47: Utf8: java/util/List
48: Utf8: get
49: Utf8: (I)Ljava/lang/Object;
50: Utf8: intValue
51: Utf8: ()I
