This Class  : ru.andrew.jclazz.apps.tester.tests.ops.Test_Return
Super Class : java.lang.Object
Implemented Interfaces:

Version: 46.0
JVM supported: 1.2 and greater

Access Flags: 33 ( PUBLIC  SUPER )

Attributes:
@SourceFile: Test_Return.java

Fields:

Methods:
<init> : (java.lang.String) : void
{
    Access Flags: 1 ( PUBLIC )

    Attributes:
    CODE
       (
        Max stack = 2
        Max locals = 2
        Attributes:
            @LineNumberTable:
                0: line 7
                4: line 8
                12: line 9
            @LocalVariableTable: 
                0+13: this (Lru/andrew/jclazz/apps/tester/tests/ops/Test_Return;), 0
                0+13: s (Ljava/lang/String;), 1
        Exceptions:
       )
    {
        0 aload_0
        1 invokespecial <init>
        4 getstatic java.lang.System.out
        7 ldc "CONSTRUCTOR" (java.lang.String)
        9 invokevirtual println
        12 return
    }
}

test1 : () : void
{
    Access Flags: 1 ( PUBLIC )

    Attributes:
    CODE
       (
        Max stack = 2
        Max locals = 1
        Attributes:
            @LineNumberTable:
                0: line 13
                8: line 14
            @LocalVariableTable: 
                0+9: this (Lru/andrew/jclazz/apps/tester/tests/ops/Test_Return;), 0
        Exceptions:
       )
    {
        0 getstatic java.lang.System.out
        3 ldc "RET VOID" (java.lang.String)
        5 invokevirtual println
        8 return
    }
}

test2 : () : boolean
{
    Access Flags: 1 ( PUBLIC )

    Attributes:
    CODE
       (
        Max stack = 1
        Max locals = 1
        Attributes:
            @LineNumberTable:
                0: line 18
            @LocalVariableTable: 
                0+2: this (Lru/andrew/jclazz/apps/tester/tests/ops/Test_Return;), 0
        Exceptions:
       )
    {
        0 iconst_1
        1 ireturn
    }
}

test3 : () : int
{
    Access Flags: 1 ( PUBLIC )

    Attributes:
    CODE
       (
        Max stack = 1
        Max locals = 1
        Attributes:
            @LineNumberTable:
                0: line 23
            @LocalVariableTable: 
                0+3: this (Lru/andrew/jclazz/apps/tester/tests/ops/Test_Return;), 0
        Exceptions:
       )
    {
        0 bipush 12 (int)
        2 ireturn
    }
}

test4 : () : long
{
    Access Flags: 1 ( PUBLIC )

    Attributes:
    CODE
       (
        Max stack = 2
        Max locals = 1
        Attributes:
            @LineNumberTable:
                0: line 28
            @LocalVariableTable: 
                0+4: this (Lru/andrew/jclazz/apps/tester/tests/ops/Test_Return;), 0
        Exceptions:
       )
    {
        0 ldc2_w 45L (long)
        3 lreturn
    }
}

test5 : () : float
{
    Access Flags: 1 ( PUBLIC )

    Attributes:
    CODE
       (
        Max stack = 1
        Max locals = 1
        Attributes:
            @LineNumberTable:
                0: line 33
            @LocalVariableTable: 
                0+3: this (Lru/andrew/jclazz/apps/tester/tests/ops/Test_Return;), 0
        Exceptions:
       )
    {
        0 ldc 12.0f (float)
        2 freturn
    }
}

test6 : () : double
{
    Access Flags: 1 ( PUBLIC )

    Attributes:
    CODE
       (
        Max stack = 2
        Max locals = 1
        Attributes:
            @LineNumberTable:
                0: line 38
            @LocalVariableTable: 
                0+4: this (Lru/andrew/jclazz/apps/tester/tests/ops/Test_Return;), 0
        Exceptions:
       )
    {
        0 ldc2_w 11.0 (double)
        3 dreturn
    }
}

test7 : () : java.lang.String
{
    Access Flags: 1 ( PUBLIC )

    Attributes:
    CODE
       (
        Max stack = 1
        Max locals = 1
        Attributes:
            @LineNumberTable:
                0: line 43
            @LocalVariableTable: 
                0+3: this (Lru/andrew/jclazz/apps/tester/tests/ops/Test_Return;), 0
        Exceptions:
       )
    {
        0 ldc "123" (java.lang.String)
        2 areturn
    }
}

test8 : (java.lang.String) : java.lang.Object
{
    Access Flags: 1 ( PUBLIC )

    Attributes:
    CODE
       (
        Max stack = 1
        Max locals = 2
        Attributes:
            @LineNumberTable:
                0: line 48
            @LocalVariableTable: 
                0+2: this (Lru/andrew/jclazz/apps/tester/tests/ops/Test_Return;), 0
                0+2: s (Ljava/lang/String;), 1
        Exceptions:
       )
    {
        0 aload_1
        1 areturn
    }
}

Constant Pool:
0: 
1: Methodref: java.lang.Object.<init> (()V)
2: Fieldref: java.io.PrintStream
3: String: "CONSTRUCTOR"
4: Methodref: java.io.PrintStream.println ((Ljava/lang/String;)V)
5: String: "RET VOID"
6: Long: 45L
7: 
8: Float: 12.0f
9: Double: 11.0
10: 
11: String: "123"
12: Class: ru.andrew.jclazz.apps.tester.tests.ops.Test_Return
13: Class: java.lang.Object
14: Utf8: <init>
15: Utf8: (Ljava/lang/String;)V
16: Utf8: Code
17: Utf8: LineNumberTable
18: Utf8: LocalVariableTable
19: Utf8: this
20: Utf8: Lru/andrew/jclazz/apps/tester/tests/ops/Test_Return;
21: Utf8: s
22: Utf8: Ljava/lang/String;
23: Utf8: test1
24: Utf8: ()V
25: Utf8: test2
26: Utf8: ()Z
27: Utf8: test3
28: Utf8: ()I
29: Utf8: test4
30: Utf8: ()J
31: Utf8: test5
32: Utf8: ()F
33: Utf8: test6
34: Utf8: ()D
35: Utf8: test7
36: Utf8: ()Ljava/lang/String;
37: Utf8: test8
38: Utf8: (Ljava/lang/String;)Ljava/lang/Object;
39: Utf8: SourceFile
40: Utf8: Test_Return.java
41: NameAndType: <init> (()V)
42: Class: java.lang.System
43: NameAndType: out (Ljava/io/PrintStream;)
44: Utf8: CONSTRUCTOR
45: Class: java.io.PrintStream
46: NameAndType: println ((Ljava/lang/String;)V)
47: Utf8: RET VOID
48: Utf8: 123
49: Utf8: ru/andrew/jclazz/apps/tester/tests/ops/Test_Return
50: Utf8: java/lang/Object
51: Utf8: java/lang/System
52: Utf8: out
53: Utf8: Ljava/io/PrintStream;
54: Utf8: java/io/PrintStream
55: Utf8: println
