This Class  : ru.andrew.jclazz.apps.tester.tests.clazz.FieldCommon
Super Class : java.lang.Object
Implemented Interfaces:

Version: 50.0
JVM supported: 1.6 and greater

Access Flags: 33 ( PUBLIC  SUPER )

Attributes:
@SourceFile: FieldCommon.java

Fields:
str1 : java.lang.String
{
    Access Flags: 1 ( PUBLIC )

    Attributes:
}

l2 : long
{
    Access Flags: 2 ( PRIVATE )

    Attributes:
}

d3 : double
{
    Access Flags: 4 ( PROTECTED )

    Attributes:
}

str4 : java.lang.String
{
    Access Flags: 17 ( PUBLIC  FINAL )

    Attributes:
        @ConstantValue: "STR4"
}

f5 : float
{
    Access Flags: 9 ( PUBLIC  STATIC )

    Attributes:
}

c6 : char
{
    Access Flags: 66 ( PRIVATE  VOLATILE )

    Attributes:
}

b7 : boolean
{
    Access Flags: 132 ( PROTECTED  TRANSIENT )

    Attributes:
}

n0 : boolean
{
    Access Flags: 17 ( PUBLIC  FINAL )

    Attributes:
        @ConstantValue: 1
}

n1 : byte
{
    Access Flags: 17 ( PUBLIC  FINAL )

    Attributes:
        @ConstantValue: 2
}

n2 : char
{
    Access Flags: 17 ( PUBLIC  FINAL )

    Attributes:
        @ConstantValue: 4
}

n3 : short
{
    Access Flags: 17 ( PUBLIC  FINAL )

    Attributes:
        @ConstantValue: 10
}

n4 : int
{
    Access Flags: 17 ( PUBLIC  FINAL )

    Attributes:
        @ConstantValue: 100
}

n5 : long
{
    Access Flags: 17 ( PUBLIC  FINAL )

    Attributes:
        @ConstantValue: 555L
}

n6 : float
{
    Access Flags: 17 ( PUBLIC  FINAL )

    Attributes:
        @ConstantValue: 33.0f
}

n7 : double
{
    Access Flags: 17 ( PUBLIC  FINAL )

    Attributes:
        @ConstantValue: 3.14
}

n8 : java.lang.String
{
    Access Flags: 17 ( PUBLIC  FINAL )

    Attributes:
        @ConstantValue: "CONST"
}

n9 : java.math.BigInteger
{
    Access Flags: 17 ( PUBLIC  FINAL )

    Attributes:
}

n10 : long
{
    Access Flags: 17 ( PUBLIC  FINAL )

    Attributes:
}

g1 : java.util.List
{
    Access Flags: 1 ( PUBLIC )

    Attributes:
        @Signature: Ljava/util/List<Ljava/lang/Number;>;
}

g2 : java.util.List
{
    Access Flags: 1 ( PUBLIC )

    Attributes:
        @Signature: Ljava/util/List<+Ljava/lang/Number;>;
}

g3 : java.util.List
{
    Access Flags: 1 ( PUBLIC )

    Attributes:
        @Signature: Ljava/util/List<-Ljava/lang/Number;>;
}

g4 : java.util.List
{
    Access Flags: 1 ( PUBLIC )

    Attributes:
        @Signature: Ljava/util/List<*>;
}


Methods:
<init> : () : void
{
    Access Flags: 1 ( PUBLIC )

    Attributes:
    CODE
       (
        Max stack = 3
        Max locals = 1
        Attributes:
            @LineNumberTable:
                0: line 32
                4: line 11
                10: line 15
                15: line 16
                20: line 17
                25: line 18
                31: line 19
                37: line 20
                44: line 21
                50: line 22
                57: line 23
                63: line 33
                73: line 34
                80: line 35
            @LocalVariableTable: 
                0+81: this (Lru/andrew/jclazz/apps/tester/tests/clazz/FieldCommon;), 0
        Exceptions:
       )
    {
        0 aload_0
        1 invokespecial <init>
        4 aload_0
        5 ldc "STR4" (java.lang.String)
        7 putfield str4
        10 aload_0
        11 iconst_1
        12 putfield n0
        15 aload_0
        16 iconst_2
        17 putfield n1
        20 aload_0
        21 iconst_4
        22 putfield n2
        25 aload_0
        26 bipush 10 (int)
        28 putfield n3
        31 aload_0
        32 bipush 100 (int)
        34 putfield n4
        37 aload_0
        38 ldc2_w 555L (long)
        41 putfield n5
        44 aload_0
        45 ldc 33.0f (float)
        47 putfield n6
        50 aload_0
        51 ldc2_w 3.14 (double)
        54 putfield n7
        57 aload_0
        58 ldc "CONST" (java.lang.String)
        60 putfield n8
        63 aload_0
        64 ldc2_w 1000L (long)
        67 invokestatic java.math.BigInteger.valueOf
        70 putfield n9
        73 aload_0
        74 ldc2_w 33L (long)
        77 putfield n10
        80 return
    }
}

<init> : (java.lang.String) : void
{
    Access Flags: 1 ( PUBLIC )

    Attributes:
    CODE
       (
        Max stack = 3
        Max locals = 2
        Attributes:
            @LineNumberTable:
                0: line 38
                4: line 11
                10: line 15
                15: line 16
                20: line 17
                25: line 18
                31: line 19
                37: line 20
                44: line 21
                50: line 22
                57: line 23
                63: line 39
                73: line 40
                80: line 41
            @LocalVariableTable: 
                0+81: this (Lru/andrew/jclazz/apps/tester/tests/clazz/FieldCommon;), 0
                0+81: str (Ljava/lang/String;), 1
        Exceptions:
       )
    {
        0 aload_0
        1 invokespecial <init>
        4 aload_0
        5 ldc "STR4" (java.lang.String)
        7 putfield str4
        10 aload_0
        11 iconst_1
        12 putfield n0
        15 aload_0
        16 iconst_2
        17 putfield n1
        20 aload_0
        21 iconst_4
        22 putfield n2
        25 aload_0
        26 bipush 10 (int)
        28 putfield n3
        31 aload_0
        32 bipush 100 (int)
        34 putfield n4
        37 aload_0
        38 ldc2_w 555L (long)
        41 putfield n5
        44 aload_0
        45 ldc 33.0f (float)
        47 putfield n6
        50 aload_0
        51 ldc2_w 3.14 (double)
        54 putfield n7
        57 aload_0
        58 ldc "CONST" (java.lang.String)
        60 putfield n8
        63 aload_0
        64 ldc2_w 1000L (long)
        67 invokestatic java.math.BigInteger.valueOf
        70 putfield n9
        73 aload_0
        74 ldc2_w 23L (long)
        77 putfield n10
        80 return
    }
}

Constant Pool:
0: 
1: Methodref: java.lang.Object.<init> (()V)
2: String: "STR4"
3: Fieldref: java.lang.String
4: Fieldref: boolean
5: Fieldref: byte
6: Fieldref: char
7: Fieldref: short
8: Fieldref: int
9: Long: 555L
10: 
11: Fieldref: long
12: Float: 33.0f
13: Fieldref: float
14: Double: 3.14
15: 
16: Fieldref: double
17: String: "CONST"
18: Fieldref: java.lang.String
19: Long: 1000L
20: 
21: Methodref: java.math.BigInteger.valueOf ((J)Ljava/math/BigInteger;)
22: Fieldref: java.math.BigInteger
23: Long: 33L
24: 
25: Fieldref: long
26: Long: 23L
27: 
28: Class: ru.andrew.jclazz.apps.tester.tests.clazz.FieldCommon
29: Class: java.lang.Object
30: Utf8: str1
31: Utf8: Ljava/lang/String;
32: Utf8: l2
33: Utf8: J
34: Utf8: d3
35: Utf8: D
36: Utf8: str4
37: Utf8: ConstantValue
38: Utf8: f5
39: Utf8: F
40: Utf8: c6
41: Utf8: C
42: Utf8: b7
43: Utf8: Z
44: Utf8: n0
45: Integer: 1
46: Utf8: n1
47: Utf8: B
48: Integer: 2
49: Utf8: n2
50: Integer: 4
51: Utf8: n3
52: Utf8: S
53: Integer: 10
54: Utf8: n4
55: Utf8: I
56: Integer: 100
57: Utf8: n5
58: Utf8: n6
59: Utf8: n7
60: Utf8: n8
61: Utf8: n9
62: Utf8: Ljava/math/BigInteger;
63: Utf8: n10
64: Utf8: g1
65: Utf8: Ljava/util/List;
66: Utf8: Signature
67: Utf8: Ljava/util/List<Ljava/lang/Number;>;
68: Utf8: g2
69: Utf8: Ljava/util/List<+Ljava/lang/Number;>;
70: Utf8: g3
71: Utf8: Ljava/util/List<-Ljava/lang/Number;>;
72: Utf8: g4
73: Utf8: Ljava/util/List<*>;
74: Utf8: <init>
75: Utf8: ()V
76: Utf8: Code
77: Utf8: LineNumberTable
78: Utf8: LocalVariableTable
79: Utf8: this
80: Utf8: Lru/andrew/jclazz/apps/tester/tests/clazz/FieldCommon;
81: Utf8: (Ljava/lang/String;)V
82: Utf8: str
83: Utf8: SourceFile
84: Utf8: FieldCommon.java
85: NameAndType: <init> (()V)
86: Utf8: STR4
87: NameAndType: str4 (Ljava/lang/String;)
88: NameAndType: n0 (Z)
89: NameAndType: n1 (B)
90: NameAndType: n2 (C)
91: NameAndType: n3 (S)
92: NameAndType: n4 (I)
93: NameAndType: n5 (J)
94: NameAndType: n6 (F)
95: NameAndType: n7 (D)
96: Utf8: CONST
97: NameAndType: n8 (Ljava/lang/String;)
98: Class: java.math.BigInteger
99: NameAndType: valueOf ((J)Ljava/math/BigInteger;)
100: NameAndType: n9 (Ljava/math/BigInteger;)
101: NameAndType: n10 (J)
102: Utf8: ru/andrew/jclazz/apps/tester/tests/clazz/FieldCommon
103: Utf8: java/lang/Object
104: Utf8: java/math/BigInteger
105: Utf8: valueOf
106: Utf8: (J)Ljava/math/BigInteger;
