This Class  : ru.andrew.jclazz.apps.tester.tests.ops.Test_Iinc
Super Class : java.lang.Object
Implemented Interfaces:

Version: 50.0
JVM supported: 1.6 and greater

Access Flags: 33 ( PUBLIC  SUPER )

Attributes:
@SourceFile: Test_Iinc.java

Fields:

Methods:
<init> : () : void
{
    Access Flags: 1 ( PUBLIC )

    Attributes:
    CODE
       (
        Max stack = 1
        Max locals = 1
        Attributes:
            @LineNumberTable:
                0: line 7
                4: line 8
            @LocalVariableTable: 
                0+5: this (Lru/andrew/jclazz/apps/tester/tests/ops/Test_Iinc;), 0
        Exceptions:
       )
    {
        0 aload_0
        1 invokespecial <init>
        4 return
    }
}

test1 : () : void
{
    Access Flags: 1 ( PUBLIC )

    Attributes:
    CODE
       (
        Max stack = 1
        Max locals = 2
        Attributes:
            @LineNumberTable:
                0: line 12
                3: line 13
                6: line 14
            @LocalVariableTable: 
                0+7: this (Lru/andrew/jclazz/apps/tester/tests/ops/Test_Iinc;), 0
                3+4: i (I), 1
        Exceptions:
       )
    {
        0 bipush 8 (int)
        2 istore_1
        3 iinc LV-1 by 1
        6 return
    }
}

test2 : () : void
{
    Access Flags: 1 ( PUBLIC )

    Attributes:
    CODE
       (
        Max stack = 1
        Max locals = 2
        Attributes:
            @LineNumberTable:
                0: line 18
                3: line 19
                9: line 20
            @LocalVariableTable: 
                0+10: this (Lru/andrew/jclazz/apps/tester/tests/ops/Test_Iinc;), 0
                3+7: i (I), 1
        Exceptions:
       )
    {
        0 bipush 8 (int)
        2 istore_1
        3 iinc LV-1 by 1000
        9 return
    }
}

Constant Pool:
0: 
1: Methodref: java.lang.Object.<init> (()V)
2: Class: ru.andrew.jclazz.apps.tester.tests.ops.Test_Iinc
3: Class: java.lang.Object
4: Utf8: <init>
5: Utf8: ()V
6: Utf8: Code
7: Utf8: LineNumberTable
8: Utf8: LocalVariableTable
9: Utf8: this
10: Utf8: Lru/andrew/jclazz/apps/tester/tests/ops/Test_Iinc;
11: Utf8: test1
12: Utf8: i
13: Utf8: I
14: Utf8: test2
15: Utf8: SourceFile
16: Utf8: Test_Iinc.java
17: NameAndType: <init> (()V)
18: Utf8: ru/andrew/jclazz/apps/tester/tests/ops/Test_Iinc
19: Utf8: java/lang/Object
