This Class  : ru.andrew.jclazz.apps.tester.tests.ops.Test_Throw
Super Class : java.lang.Object
Implemented Interfaces:

Version: 50.0
JVM supported: 1.6 and greater

Access Flags: 33 ( PUBLIC  SUPER )

Attributes:
@SourceFile: Test_Throw.java

Fields:

Methods:
<init> : () : void
{
    Access Flags: 1 ( PUBLIC )

    Attributes:
    CODE
       (
        Max stack = 1
        Max locals = 1
        Attributes:
            @LineNumberTable:
                0: line 7
                4: line 8
            @LocalVariableTable: 
                0+5: this (Lru/andrew/jclazz/apps/tester/tests/ops/Test_Throw;), 0
        Exceptions:
       )
    {
        0 aload_0
        1 invokespecial <init>
        4 return
    }
}

test1 : (int, java.lang.RuntimeException) : void
{
    Access Flags: 1 ( PUBLIC )

    Attributes:
    CODE
       (
        Max stack = 2
        Max locals = 3
        Attributes:
            @LineNumberTable:
                0: line 12
                5: line 14
                7: line 16
            @LocalVariableTable: 
                0+8: this (Lru/andrew/jclazz/apps/tester/tests/ops/Test_Throw;), 0
                0+8: i (I), 1
                0+8: re (Ljava/lang/RuntimeException;), 2
            @StackMapTable: 
                SameFrame (+7): 
            
        Exceptions:
       )
    {
        0 iload_1
        1 iconst_4
        2 if_icmpne 7
        5 aload_2
        6 athrow
        7 return
    }
}

Constant Pool:
0: 
1: Methodref: java.lang.Object.<init> (()V)
2: Class: ru.andrew.jclazz.apps.tester.tests.ops.Test_Throw
3: Class: java.lang.Object
4: Utf8: <init>
5: Utf8: ()V
6: Utf8: Code
7: Utf8: LineNumberTable
8: Utf8: LocalVariableTable
9: Utf8: this
10: Utf8: Lru/andrew/jclazz/apps/tester/tests/ops/Test_Throw;
11: Utf8: test1
12: Utf8: (ILjava/lang/RuntimeException;)V
13: Utf8: i
14: Utf8: I
15: Utf8: re
16: Utf8: Ljava/lang/RuntimeException;
17: Utf8: StackMapTable
18: Utf8: SourceFile
19: Utf8: Test_Throw.java
20: NameAndType: <init> (()V)
21: Utf8: ru/andrew/jclazz/apps/tester/tests/ops/Test_Throw
22: Utf8: java/lang/Object
