This Class  : ru.andrew.jclazz.apps.tester.tests.ops.Test_TypeConversion
Super Class : java.lang.Object
Implemented Interfaces:

Version: 50.0
JVM supported: 1.6 and greater

Access Flags: 33 ( PUBLIC  SUPER )

Attributes:
@SourceFile: Test_TypeConversion.java

Fields:

Methods:
<init> : () : void
{
    Access Flags: 1 ( PUBLIC )

    Attributes:
    CODE
       (
        Max stack = 1
        Max locals = 1
        Attributes:
            @LineNumberTable:
                0: line 7
                4: line 8
            @LocalVariableTable: 
                0+5: this (Lru/andrew/jclazz/apps/tester/tests/ops/Test_TypeConversion;), 0
        Exceptions:
       )
    {
        0 aload_0
        1 invokespecial <init>
        4 return
    }
}

test1 : () : void
{
    Access Flags: 1 ( PUBLIC )

    Attributes:
    CODE
       (
        Max stack = 2
        Max locals = 10
        Attributes:
            @LineNumberTable:
                0: line 12
                2: line 13
                5: line 14
                9: line 15
                13: line 16
                17: line 17
                21: line 18
                25: line 19
            @LocalVariableTable: 
                0+26: this (Lru/andrew/jclazz/apps/tester/tests/ops/Test_TypeConversion;), 0
                2+24: i (I), 1
                5+21: l (J), 2
                9+17: f (F), 4
                13+13: d (D), 5
                17+9: b (B), 7
                21+5: c (C), 8
                25+1: s (S), 9
        Exceptions:
       )
    {
        0 iconst_4
        1 istore_1
        2 iload_1
        3 i2l
        4 lstore_2
        5 iload_1
        6 i2f
        7 fstore LV-4
        9 iload_1
        10 i2d
        11 dstore LV-5
        13 iload_1
        14 i2b
        15 istore LV-7
        17 iload_1
        18 i2c
        19 istore LV-8
        21 iload_1
        22 i2s
        23 istore LV-9
        25 return
    }
}

test2 : () : void
{
    Access Flags: 1 ( PUBLIC )

    Attributes:
    CODE
       (
        Max stack = 2
        Max locals = 7
        Attributes:
            @LineNumberTable:
                0: line 23
                4: line 24
                7: line 25
                11: line 26
                15: line 27
            @LocalVariableTable: 
                0+16: this (Lru/andrew/jclazz/apps/tester/tests/ops/Test_TypeConversion;), 0
                4+12: l (J), 1
                7+9: i (I), 3
                11+5: f (F), 4
                15+1: d (D), 5
        Exceptions:
       )
    {
        0 ldc2_w 12L (long)
        3 lstore_1
        4 lload_1
        5 l2i
        6 istore_3
        7 lload_1
        8 l2f
        9 fstore LV-4
        11 lload_1
        12 l2d
        13 dstore LV-5
        15 return
    }
}

test3 : () : void
{
    Access Flags: 1 ( PUBLIC )

    Attributes:
    CODE
       (
        Max stack = 2
        Max locals = 7
        Attributes:
            @LineNumberTable:
                0: line 31
                3: line 32
                6: line 33
                9: line 34
                13: line 35
            @LocalVariableTable: 
                0+14: this (Lru/andrew/jclazz/apps/tester/tests/ops/Test_TypeConversion;), 0
                3+11: f (F), 1
                6+8: i (I), 2
                9+5: l (J), 3
                13+1: d (D), 5
        Exceptions:
       )
    {
        0 ldc 12.0f (float)
        2 fstore_1
        3 fload_1
        4 f2i
        5 istore_2
        6 fload_1
        7 f2l
        8 lstore_3
        9 fload_1
        10 f2d
        11 dstore LV-5
        13 return
    }
}

test4 : () : void
{
    Access Flags: 1 ( PUBLIC )

    Attributes:
    CODE
       (
        Max stack = 2
        Max locals = 7
        Attributes:
            @LineNumberTable:
                0: line 39
                4: line 40
                7: line 41
                11: line 42
                15: line 43
            @LocalVariableTable: 
                0+16: this (Lru/andrew/jclazz/apps/tester/tests/ops/Test_TypeConversion;), 0
                4+12: d (D), 1
                7+9: i (I), 3
                11+5: l (J), 4
                15+1: f (F), 6
        Exceptions:
       )
    {
        0 ldc2_w 12.0 (double)
        3 dstore_1
        4 dload_1
        5 d2i
        6 istore_3
        7 dload_1
        8 d2l
        9 lstore LV-4
        11 dload_1
        12 d2f
        13 fstore LV-6
        15 return
    }
}

Constant Pool:
0: 
1: Methodref: java.lang.Object.<init> (()V)
2: Long: 12L
3: 
4: Float: 12.0f
5: Double: 12.0
6: 
7: Class: ru.andrew.jclazz.apps.tester.tests.ops.Test_TypeConversion
8: Class: java.lang.Object
9: Utf8: <init>
10: Utf8: ()V
11: Utf8: Code
12: Utf8: LineNumberTable
13: Utf8: LocalVariableTable
14: Utf8: this
15: Utf8: Lru/andrew/jclazz/apps/tester/tests/ops/Test_TypeConversion;
16: Utf8: test1
17: Utf8: i
18: Utf8: I
19: Utf8: l
20: Utf8: J
21: Utf8: f
22: Utf8: F
23: Utf8: d
24: Utf8: D
25: Utf8: b
26: Utf8: B
27: Utf8: c
28: Utf8: C
29: Utf8: s
30: Utf8: S
31: Utf8: test2
32: Utf8: test3
33: Utf8: test4
34: Utf8: SourceFile
35: Utf8: Test_TypeConversion.java
36: NameAndType: <init> (()V)
37: Utf8: ru/andrew/jclazz/apps/tester/tests/ops/Test_TypeConversion
38: Utf8: java/lang/Object
