This Class  : ru.andrew.jclazz.apps.tester.tests.ops.Test_New
Super Class : java.lang.Object
Implemented Interfaces:

Version: 46.0
JVM supported: 1.2 and greater

Access Flags: 33 ( PUBLIC  SUPER )

Attributes:
@SourceFile: Test_New.java

Fields:

Methods:
<init> : () : void
{
    Access Flags: 1 ( PUBLIC )

    Attributes:
    CODE
       (
        Max stack = 1
        Max locals = 1
        Attributes:
            @LineNumberTable:
                0: line 7
                4: line 8
            @LocalVariableTable: 
                0+5: this (Lru/andrew/jclazz/apps/tester/tests/ops/Test_New;), 0
        Exceptions:
       )
    {
        0 aload_0
        1 invokespecial <init>
        4 return
    }
}

test1 : () : void
{
    Access Flags: 1 ( PUBLIC )

    Attributes:
    CODE
       (
        Max stack = 3
        Max locals = 3
        Attributes:
            @LineNumberTable:
                0: line 12
                10: line 13
                19: line 14
            @LocalVariableTable: 
                0+20: this (Lru/andrew/jclazz/apps/tester/tests/ops/Test_New;), 0
                10+10: s1 (Ljava/lang/String;), 1
                19+1: o1 (Ljava/lang/Object;), 2
        Exceptions:
       )
    {
        0 new java.lang.String
        3 dup
        4 ldc "123" (java.lang.String)
        6 invokespecial <init>
        9 astore_1
        10 new java.lang.Integer
        13 dup
        14 iconst_4
        15 invokespecial <init>
        18 astore_2
        19 return
    }
}

Constant Pool:
0: 
1: Methodref: java.lang.Object.<init> (()V)
2: Class: java.lang.String
3: String: "123"
4: Methodref: java.lang.String.<init> ((Ljava/lang/String;)V)
5: Class: java.lang.Integer
6: Methodref: java.lang.Integer.<init> ((I)V)
7: Class: ru.andrew.jclazz.apps.tester.tests.ops.Test_New
8: Class: java.lang.Object
9: Utf8: <init>
10: Utf8: ()V
11: Utf8: Code
12: Utf8: LineNumberTable
13: Utf8: LocalVariableTable
14: Utf8: this
15: Utf8: Lru/andrew/jclazz/apps/tester/tests/ops/Test_New;
16: Utf8: test1
17: Utf8: s1
18: Utf8: Ljava/lang/String;
19: Utf8: o1
20: Utf8: Ljava/lang/Object;
21: Utf8: SourceFile
22: Utf8: Test_New.java
23: NameAndType: <init> (()V)
24: Utf8: java/lang/String
25: Utf8: 123
26: NameAndType: <init> ((Ljava/lang/String;)V)
27: Utf8: java/lang/Integer
28: NameAndType: <init> ((I)V)
29: Utf8: ru/andrew/jclazz/apps/tester/tests/ops/Test_New
30: Utf8: java/lang/Object
31: Utf8: (Ljava/lang/String;)V
32: Utf8: (I)V
