This Class  : ru.andrew.jclazz.apps.tester.tests.ops.Test_Switch
Super Class : java.lang.Object
Implemented Interfaces:

Version: 50.0
JVM supported: 1.6 and greater

Access Flags: 33 ( PUBLIC  SUPER )

Attributes:
@SourceFile: Test_Switch.java

Fields:

Methods:
<init> : () : void
{
    Access Flags: 1 ( PUBLIC )

    Attributes:
    CODE
       (
        Max stack = 1
        Max locals = 1
        Attributes:
            @LineNumberTable:
                0: line 7
                4: line 8
            @LocalVariableTable: 
                0+5: this (Lru/andrew/jclazz/apps/tester/tests/ops/Test_Switch;), 0
        Exceptions:
       )
    {
        0 aload_0
        1 invokespecial <init>
        4 return
    }
}

testSwitch1 : (int) : void
{
    Access Flags: 1 ( PUBLIC )

    Attributes:
    CODE
       (
        Max stack = 2
        Max locals = 2
        Attributes:
            @LineNumberTable:
                0: line 12
                8: line 13
                44: line 16
                52: line 17
                55: line 19
                63: line 20
                66: line 22
                74: line 23
                75: line 25
                83: line 27
                91: line 28
            @LocalVariableTable: 
                0+92: this (Lru/andrew/jclazz/apps/tester/tests/ops/Test_Switch;), 0
                0+92: i (I), 1
            @StackMapTable: 
                SameFrame (+44): 
                SameFrame (+10): 
                SameFrame (+10): 
                SameFrame (+8): 
                SameFrame (+7): 
            
        Exceptions:
       )
    {
        0 getstatic java.lang.System.out
        3 ldc "BEFORE SWITCH" (java.lang.String)
        5 invokevirtual println
        8 iload_1
        9 lookupswitch default:75 0:44 10:55 50:66 
        44 getstatic java.lang.System.out
        47 ldc "0" (java.lang.String)
        49 invokevirtual println
        52 goto 83
        55 getstatic java.lang.System.out
        58 ldc "10" (java.lang.String)
        60 invokevirtual println
        63 goto 83
        66 getstatic java.lang.System.out
        69 ldc "50" (java.lang.String)
        71 invokevirtual println
        74 return
        75 getstatic java.lang.System.out
        78 ldc "DEFAULT" (java.lang.String)
        80 invokevirtual println
        83 getstatic java.lang.System.out
        86 ldc "AFTER SWITCH" (java.lang.String)
        88 invokevirtual println
        91 return
    }
}

testSwitch2 : (int) : void
{
    Access Flags: 1 ( PUBLIC )

    Attributes:
    CODE
       (
        Max stack = 2
        Max locals = 2
        Attributes:
            @LineNumberTable:
                0: line 32
                8: line 33
                36: line 36
                44: line 38
                52: line 39
                55: line 41
                63: line 42
                64: line 44
                72: line 46
                80: line 47
            @LocalVariableTable: 
                0+81: this (Lru/andrew/jclazz/apps/tester/tests/ops/Test_Switch;), 0
                0+81: i (I), 1
            @StackMapTable: 
                SameFrame (+36): 
                SameFrame (+7): 
                SameFrame (+10): 
                SameFrame (+8): 
                SameFrame (+7): 
            
        Exceptions:
       )
    {
        0 getstatic java.lang.System.out
        3 ldc "BEFORE SWITCH" (java.lang.String)
        5 invokevirtual println
        8 iload_1
        9 tableswitch default:64 0:36 1:44 2:55 
        36 getstatic java.lang.System.out
        39 ldc "0" (java.lang.String)
        41 invokevirtual println
        44 getstatic java.lang.System.out
        47 ldc "1" (java.lang.String)
        49 invokevirtual println
        52 goto 72
        55 getstatic java.lang.System.out
        58 ldc "2" (java.lang.String)
        60 invokevirtual println
        63 return
        64 getstatic java.lang.System.out
        67 ldc "DEFAULT" (java.lang.String)
        69 invokevirtual println
        72 getstatic java.lang.System.out
        75 ldc "AFTER SWITCH" (java.lang.String)
        77 invokevirtual println
        80 return
    }
}

testSwitch3 : (int) : void
{
    Access Flags: 1 ( PUBLIC )

    Attributes:
    CODE
       (
        Max stack = 2
        Max locals = 2
        Attributes:
            @LineNumberTable:
                0: line 51
                8: line 52
                28: line 55
                36: line 57
                44: line 58
            @LocalVariableTable: 
                0+45: this (Lru/andrew/jclazz/apps/tester/tests/ops/Test_Switch;), 0
                0+45: i (I), 1
            @StackMapTable: 
                SameFrame (+28): 
                SameFrame (+7): 
            
        Exceptions:
       )
    {
        0 getstatic java.lang.System.out
        3 ldc "BEFORE SWITCH" (java.lang.String)
        5 invokevirtual println
        8 iload_1
        9 lookupswitch default:36 0:28 
        28 getstatic java.lang.System.out
        31 ldc "0" (java.lang.String)
        33 invokevirtual println
        36 getstatic java.lang.System.out
        39 ldc "AFTER SWITCH" (java.lang.String)
        41 invokevirtual println
        44 return
    }
}

testSwitch4 : (int) : void
{
    Access Flags: 1 ( PUBLIC )

    Attributes:
    CODE
       (
        Max stack = 2
        Max locals = 2
        Attributes:
            @LineNumberTable:
                0: line 62
                8: line 63
                36: line 67
                44: line 68
                47: line 70
                55: line 71
                56: line 73
                64: line 74
            @LocalVariableTable: 
                0+65: this (Lru/andrew/jclazz/apps/tester/tests/ops/Test_Switch;), 0
                0+65: i (I), 1
            @StackMapTable: 
                SameFrame (+36): 
                SameFrame (+10): 
                SameFrame (+8): 
            
        Exceptions:
       )
    {
        0 getstatic java.lang.System.out
        3 ldc "BEFORE SWITCH" (java.lang.String)
        5 invokevirtual println
        8 iload_1
        9 tableswitch default:56 0:36 1:36 2:47 
        36 getstatic java.lang.System.out
        39 ldc "1" (java.lang.String)
        41 invokevirtual println
        44 goto 56
        47 getstatic java.lang.System.out
        50 ldc "2" (java.lang.String)
        52 invokevirtual println
        55 return
        56 getstatic java.lang.System.out
        59 ldc "AFTER SWITCH" (java.lang.String)
        61 invokevirtual println
        64 return
    }
}

Constant Pool:
0: 
1: Methodref: java.lang.Object.<init> (()V)
2: Fieldref: java.io.PrintStream
3: String: "BEFORE SWITCH"
4: Methodref: java.io.PrintStream.println ((Ljava/lang/String;)V)
5: String: "0"
6: String: "10"
7: String: "50"
8: String: "DEFAULT"
9: String: "AFTER SWITCH"
10: String: "1"
11: String: "2"
12: Class: ru.andrew.jclazz.apps.tester.tests.ops.Test_Switch
13: Class: java.lang.Object
14: Utf8: <init>
15: Utf8: ()V
16: Utf8: Code
17: Utf8: LineNumberTable
18: Utf8: LocalVariableTable
19: Utf8: this
20: Utf8: Lru/andrew/jclazz/apps/tester/tests/ops/Test_Switch;
21: Utf8: testSwitch1
22: Utf8: (I)V
23: Utf8: i
24: Utf8: I
25: Utf8: StackMapTable
26: Utf8: testSwitch2
27: Utf8: testSwitch3
28: Utf8: testSwitch4
29: Utf8: SourceFile
30: Utf8: Test_Switch.java
31: NameAndType: <init> (()V)
32: Class: java.lang.System
33: NameAndType: out (Ljava/io/PrintStream;)
34: Utf8: BEFORE SWITCH
35: Class: java.io.PrintStream
36: NameAndType: println ((Ljava/lang/String;)V)
37: Utf8: 0
38: Utf8: 10
39: Utf8: 50
40: Utf8: DEFAULT
41: Utf8: AFTER SWITCH
42: Utf8: 1
43: Utf8: 2
44: Utf8: ru/andrew/jclazz/apps/tester/tests/ops/Test_Switch
45: Utf8: java/lang/Object
46: Utf8: java/lang/System
47: Utf8: out
48: Utf8: Ljava/io/PrintStream;
49: Utf8: java/io/PrintStream
50: Utf8: println
51: Utf8: (Ljava/lang/String;)V
