This Class  : ru.andrew.jclazz.apps.tester.tests.blocks.LoopIfContinue
Super Class : java.lang.Object
Implemented Interfaces:

Version: 50.0
JVM supported: 1.6 and greater

Access Flags: 33 ( PUBLIC  SUPER )

Attributes:
@SourceFile: LoopIfContinue.java

Fields:

Methods:
<init> : () : void
{
    Access Flags: 1 ( PUBLIC )

    Attributes:
    CODE
       (
        Max stack = 1
        Max locals = 1
        Attributes:
            @LineNumberTable:
                0: line 7
                4: line 8
            @LocalVariableTable: 
                0+5: this (Lru/andrew/jclazz/apps/tester/tests/blocks/LoopIfContinue;), 0
        Exceptions:
       )
    {
        0 aload_0
        1 invokespecial <init>
        4 return
    }
}

test1 : () : void
{
    Access Flags: 1 ( PUBLIC )

    Attributes:
    CODE
       (
        Max stack = 2
        Max locals = 2
        Attributes:
            @LineNumberTable:
                0: line 12
                2: line 13
                8: line 15
                16: line 16
                21: line 18
                29: line 19
                32: line 21
                35: line 22
                46: line 24
            @LocalVariableTable: 
                0+47: this (Lru/andrew/jclazz/apps/tester/tests/blocks/LoopIfContinue;), 0
                2+45: i (I), 1
            @StackMapTable: 
                AppendFrame (+2): additional locals - Integer
                SameFrame (+29): 
                SameFrame (+13): 
            
        Exceptions:
       )
    {
        0 iconst_0
        1 istore_1
        2 iload_1
        3 bipush 10 (int)
        5 if_icmpge 46
        8 getstatic java.lang.System.out
        11 ldc "START LOOP" (java.lang.String)
        13 invokevirtual println
        16 iload_1
        17 iconst_5
        18 if_icmpne 32
        21 getstatic java.lang.System.out
        24 ldc "IF" (java.lang.String)
        26 invokevirtual println
        29 goto 2
        32 iinc LV-1 by 1
        35 getstatic java.lang.System.out
        38 ldc "END LOOP" (java.lang.String)
        40 invokevirtual println
        43 goto 2
        46 return
    }
}

test2 : () : void
{
    Access Flags: 1 ( PUBLIC )

    Attributes:
    CODE
       (
        Max stack = 2
        Max locals = 2
        Attributes:
            @LineNumberTable:
                0: line 28
                2: line 29
                8: line 31
                16: line 32
                21: line 34
                32: line 38
                38: line 40
                46: line 41
                49: line 43
                57: line 45
                60: line 46
                71: line 48
            @LocalVariableTable: 
                0+72: this (Lru/andrew/jclazz/apps/tester/tests/blocks/LoopIfContinue;), 0
                2+70: i (I), 1
            @StackMapTable: 
                AppendFrame (+2): additional locals - Integer
                SameFrame (+29): 
                SameFrame (+16): 
                SameFrame (+7): 
                SameFrame (+13): 
            
        Exceptions:
       )
    {
        0 iconst_0
        1 istore_1
        2 iload_1
        3 bipush 10 (int)
        5 if_icmpge 71
        8 getstatic java.lang.System.out
        11 ldc "START LOOP" (java.lang.String)
        13 invokevirtual println
        16 iload_1
        17 iconst_5
        18 if_icmpne 32
        21 getstatic java.lang.System.out
        24 ldc "IF" (java.lang.String)
        26 invokevirtual println
        29 goto 57
        32 iload_1
        33 bipush 6 (int)
        35 if_icmpne 49
        38 getstatic java.lang.System.out
        41 ldc "IFELSE" (java.lang.String)
        43 invokevirtual println
        46 goto 2
        49 getstatic java.lang.System.out
        52 ldc "ELSE" (java.lang.String)
        54 invokevirtual println
        57 iinc LV-1 by 1
        60 getstatic java.lang.System.out
        63 ldc "END LOOP" (java.lang.String)
        65 invokevirtual println
        68 goto 2
        71 return
    }
}

test3 : () : void
{
    Access Flags: 1 ( PUBLIC )

    Attributes:
    CODE
       (
        Max stack = 2
        Max locals = 2
        Attributes:
            @LineNumberTable:
                0: line 52
                2: line 53
                8: line 55
                16: line 56
                21: line 58
                32: line 62
                40: line 64
                46: line 66
            @LocalVariableTable: 
                0+47: this (Lru/andrew/jclazz/apps/tester/tests/blocks/LoopIfContinue;), 0
                2+45: i (I), 1
            @StackMapTable: 
                AppendFrame (+2): additional locals - Integer
                SameFrame (+29): 
                SameFrame (+7): 
                SameFrame (+5): 
            
        Exceptions:
       )
    {
        0 iconst_0
        1 istore_1
        2 iload_1
        3 bipush 10 (int)
        5 if_icmpge 46
        8 getstatic java.lang.System.out
        11 ldc "START LOOP" (java.lang.String)
        13 invokevirtual println
        16 iload_1
        17 iconst_5
        18 if_icmpne 32
        21 getstatic java.lang.System.out
        24 ldc "IF" (java.lang.String)
        26 invokevirtual println
        29 goto 40
        32 getstatic java.lang.System.out
        35 ldc "END LOOP" (java.lang.String)
        37 invokevirtual println
        40 iinc LV-1 by 1
        43 goto 2
        46 return
    }
}

test4 : () : void
{
    Access Flags: 1 ( PUBLIC )

    Attributes:
    CODE
       (
        Max stack = 2
        Max locals = 2
        Attributes:
            @LineNumberTable:
                0: line 70
                2: line 71
                8: line 73
                16: line 74
                21: line 76
                32: line 80
                38: line 82
                46: line 83
                49: line 85
                57: line 87
                65: line 71
                71: line 89
            @LocalVariableTable: 
                0+72: this (Lru/andrew/jclazz/apps/tester/tests/blocks/LoopIfContinue;), 0
                2+70: i (I), 1
            @StackMapTable: 
                AppendFrame (+2): additional locals - Integer
                SameFrame (+29): 
                SameFrame (+16): 
                SameFrame (+7): 
                SameFrame (+7): 
                SameFrame (+5): 
            
        Exceptions:
       )
    {
        0 iconst_0
        1 istore_1
        2 iload_1
        3 bipush 10 (int)
        5 if_icmpge 71
        8 getstatic java.lang.System.out
        11 ldc "START LOOP" (java.lang.String)
        13 invokevirtual println
        16 iload_1
        17 iconst_5
        18 if_icmpne 32
        21 getstatic java.lang.System.out
        24 ldc "IF" (java.lang.String)
        26 invokevirtual println
        29 goto 57
        32 iload_1
        33 bipush 6 (int)
        35 if_icmpne 49
        38 getstatic java.lang.System.out
        41 ldc "IFELSE" (java.lang.String)
        43 invokevirtual println
        46 goto 65
        49 getstatic java.lang.System.out
        52 ldc "ELSE" (java.lang.String)
        54 invokevirtual println
        57 getstatic java.lang.System.out
        60 ldc "END LOOP" (java.lang.String)
        62 invokevirtual println
        65 iinc LV-1 by 1
        68 goto 2
        71 return
    }
}

test5 : () : void
{
    Access Flags: 1 ( PUBLIC )

    Attributes:
    CODE
       (
        Max stack = 2
        Max locals = 2
        Attributes:
            @LineNumberTable:
                0: line 93
                2: line 96
                10: line 97
                15: line 99
                26: line 103
                29: line 104
                37: line 107
                43: line 108
            @LocalVariableTable: 
                0+44: this (Lru/andrew/jclazz/apps/tester/tests/blocks/LoopIfContinue;), 0
                2+42: i (I), 1
            @StackMapTable: 
                AppendFrame (+2): additional locals - Integer
                SameFrame (+23): 
                SameFrame (+10): 
            
        Exceptions:
       )
    {
        0 iconst_0
        1 istore_1
        2 getstatic java.lang.System.out
        5 ldc "START LOOP" (java.lang.String)
        7 invokevirtual println
        10 iload_1
        11 iconst_5
        12 if_icmpne 26
        15 getstatic java.lang.System.out
        18 ldc "IF" (java.lang.String)
        20 invokevirtual println
        23 goto 37
        26 iinc LV-1 by 1
        29 getstatic java.lang.System.out
        32 ldc "END LOOP" (java.lang.String)
        34 invokevirtual println
        37 iload_1
        38 bipush 10 (int)
        40 if_icmplt 2
        43 return
    }
}

test6 : () : void
{
    Access Flags: 1 ( PUBLIC )

    Attributes:
    CODE
       (
        Max stack = 2
        Max locals = 2
        Attributes:
            @LineNumberTable:
                0: line 112
                2: line 115
                10: line 116
                15: line 118
                26: line 122
                32: line 124
                40: line 125
                43: line 127
                51: line 129
                54: line 130
                62: line 132
                68: line 133
            @LocalVariableTable: 
                0+69: this (Lru/andrew/jclazz/apps/tester/tests/blocks/LoopIfContinue;), 0
                2+67: i (I), 1
            @StackMapTable: 
                AppendFrame (+2): additional locals - Integer
                SameFrame (+23): 
                SameFrame (+16): 
                SameFrame (+7): 
                SameFrame (+10): 
            
        Exceptions:
       )
    {
        0 iconst_0
        1 istore_1
        2 getstatic java.lang.System.out
        5 ldc "START LOOP" (java.lang.String)
        7 invokevirtual println
        10 iload_1
        11 iconst_5
        12 if_icmpne 26
        15 getstatic java.lang.System.out
        18 ldc "IF" (java.lang.String)
        20 invokevirtual println
        23 goto 51
        26 iload_1
        27 bipush 6 (int)
        29 if_icmpne 43
        32 getstatic java.lang.System.out
        35 ldc "IFELSE" (java.lang.String)
        37 invokevirtual println
        40 goto 62
        43 getstatic java.lang.System.out
        46 ldc "ELSE" (java.lang.String)
        48 invokevirtual println
        51 iinc LV-1 by 1
        54 getstatic java.lang.System.out
        57 ldc "END LOOP" (java.lang.String)
        59 invokevirtual println
        62 iload_1
        63 bipush 10 (int)
        65 if_icmplt 2
        68 return
    }
}

test7 : () : void
{
    Access Flags: 1 ( PUBLIC )

    Attributes:
    CODE
       (
        Max stack = 2
        Max locals = 2
        Attributes:
            @LineNumberTable:
                0: line 137
                2: line 138
                8: line 140
                16: line 141
                21: line 143
                32: line 145
                38: line 147
                49: line 151
                57: line 152
                60: line 154
                63: line 155
                74: line 157
            @LocalVariableTable: 
                0+75: this (Lru/andrew/jclazz/apps/tester/tests/blocks/LoopIfContinue;), 0
                2+73: i (I), 1
            @StackMapTable: 
                AppendFrame (+2): additional locals - Integer
                SameFrame (+29): 
                SameFrame (+16): 
                SameFrame (+10): 
                SameFrame (+13): 
            
        Exceptions:
       )
    {
        0 iconst_0
        1 istore_1
        2 iload_1
        3 bipush 10 (int)
        5 if_icmpge 74
        8 getstatic java.lang.System.out
        11 ldc "START LOOP" (java.lang.String)
        13 invokevirtual println
        16 iload_1
        17 iconst_5
        18 if_icmpne 32
        21 getstatic java.lang.System.out
        24 ldc "IF" (java.lang.String)
        26 invokevirtual println
        29 goto 60
        32 iload_1
        33 bipush 6 (int)
        35 if_icmpne 49
        38 getstatic java.lang.System.out
        41 ldc "IFELSE" (java.lang.String)
        43 invokevirtual println
        46 goto 60
        49 getstatic java.lang.System.out
        52 ldc "ELSE" (java.lang.String)
        54 invokevirtual println
        57 goto 2
        60 iinc LV-1 by 1
        63 getstatic java.lang.System.out
        66 ldc "END LOOP" (java.lang.String)
        68 invokevirtual println
        71 goto 2
        74 return
    }
}

test8 : () : void
{
    Access Flags: 1 ( PUBLIC )

    Attributes:
    CODE
       (
        Max stack = 2
        Max locals = 2
        Attributes:
            @LineNumberTable:
                0: line 161
                2: line 162
                8: line 164
                16: line 165
                21: line 167
                32: line 171
                38: line 173
                46: line 174
                49: line 176
                55: line 178
                66: line 182
                74: line 185
                77: line 186
                88: line 188
            @LocalVariableTable: 
                0+89: this (Lru/andrew/jclazz/apps/tester/tests/blocks/LoopIfContinue;), 0
                2+87: i (I), 1
            @StackMapTable: 
                AppendFrame (+2): additional locals - Integer
                SameFrame (+29): 
                SameFrame (+16): 
                SameFrame (+16): 
                SameFrame (+7): 
                SameFrame (+13): 
            
        Exceptions:
       )
    {
        0 iconst_0
        1 istore_1
        2 iload_1
        3 bipush 10 (int)
        5 if_icmpge 88
        8 getstatic java.lang.System.out
        11 ldc "START LOOP" (java.lang.String)
        13 invokevirtual println
        16 iload_1
        17 iconst_5
        18 if_icmpne 32
        21 getstatic java.lang.System.out
        24 ldc "IF" (java.lang.String)
        26 invokevirtual println
        29 goto 74
        32 iload_1
        33 bipush 6 (int)
        35 if_icmpne 49
        38 getstatic java.lang.System.out
        41 ldc "IFELSE" (java.lang.String)
        43 invokevirtual println
        46 goto 2
        49 iload_1
        50 bipush 7 (int)
        52 if_icmpne 66
        55 getstatic java.lang.System.out
        58 ldc "ELSE" (java.lang.String)
        60 invokevirtual println
        63 goto 74
        66 getstatic java.lang.System.out
        69 ldc "ELSE2" (java.lang.String)
        71 invokevirtual println
        74 iinc LV-1 by 1
        77 getstatic java.lang.System.out
        80 ldc "END LOOP" (java.lang.String)
        82 invokevirtual println
        85 goto 2
        88 return
    }
}

test9 : (int, int, int) : void
{
    Access Flags: 1 ( PUBLIC )

    Attributes:
    CODE
       (
        Max stack = 2
        Max locals = 5
        Attributes:
            @LineNumberTable:
                0: line 192
                3: line 193
                10: line 195
                18: line 196
                41: line 198
                49: line 199
                52: line 201
                55: line 202
                66: line 204
            @LocalVariableTable: 
                0+67: this (Lru/andrew/jclazz/apps/tester/tests/blocks/LoopIfContinue;), 0
                0+67: i2 (I), 1
                0+67: i3 (I), 2
                0+67: i4 (I), 3
                3+64: i (I), 4
            @StackMapTable: 
                AppendFrame (+3): additional locals - Integer
                SameFrame (+26): 
                SameFrame (+10): 
                SameFrame (+10): 
                SameFrame (+13): 
            
        Exceptions:
       )
    {
        0 iconst_0
        1 istore LV-4
        3 iload LV-4
        5 bipush 10 (int)
        7 if_icmpge 66
        10 getstatic java.lang.System.out
        13 ldc "START LOOP" (java.lang.String)
        15 invokevirtual println
        18 iload LV-4
        20 iconst_5
        21 if_icmpeq 30
        24 iload_1
        25 bipush 7 (int)
        27 if_icmple 52
        30 iload_2
        31 bipush 6 (int)
        33 if_icmple 41
        36 iconst_0
        37 iload_3
        38 if_icmpeq 52
        41 getstatic java.lang.System.out
        44 ldc "IF" (java.lang.String)
        46 invokevirtual println
        49 goto 3
        52 iinc LV-4 by 1
        55 getstatic java.lang.System.out
        58 ldc "END LOOP" (java.lang.String)
        60 invokevirtual println
        63 goto 3
        66 return
    }
}

Constant Pool:
0: 
1: Methodref: java.lang.Object.<init> (()V)
2: Fieldref: java.io.PrintStream
3: String: "START LOOP"
4: Methodref: java.io.PrintStream.println ((Ljava/lang/String;)V)
5: String: "IF"
6: String: "END LOOP"
7: String: "IFELSE"
8: String: "ELSE"
9: String: "ELSE2"
10: Class: ru.andrew.jclazz.apps.tester.tests.blocks.LoopIfContinue
11: Class: java.lang.Object
12: Utf8: <init>
13: Utf8: ()V
14: Utf8: Code
15: Utf8: LineNumberTable
16: Utf8: LocalVariableTable
17: Utf8: this
18: Utf8: Lru/andrew/jclazz/apps/tester/tests/blocks/LoopIfContinue;
19: Utf8: test1
20: Utf8: i
21: Utf8: I
22: Utf8: StackMapTable
23: Utf8: test2
24: Utf8: test3
25: Utf8: test4
26: Utf8: test5
27: Utf8: test6
28: Utf8: test7
29: Utf8: test8
30: Utf8: test9
31: Utf8: (III)V
32: Utf8: i2
33: Utf8: i3
34: Utf8: i4
35: Utf8: SourceFile
36: Utf8: LoopIfContinue.java
37: NameAndType: <init> (()V)
38: Class: java.lang.System
39: NameAndType: out (Ljava/io/PrintStream;)
40: Utf8: START LOOP
41: Class: java.io.PrintStream
42: NameAndType: println ((Ljava/lang/String;)V)
43: Utf8: IF
44: Utf8: END LOOP
45: Utf8: IFELSE
46: Utf8: ELSE
47: Utf8: ELSE2
48: Utf8: ru/andrew/jclazz/apps/tester/tests/blocks/LoopIfContinue
49: Utf8: java/lang/Object
50: Utf8: java/lang/System
51: Utf8: out
52: Utf8: Ljava/io/PrintStream;
53: Utf8: java/io/PrintStream
54: Utf8: println
55: Utf8: (Ljava/lang/String;)V
