This Class  : ru.andrew.jclazz.apps.tester.tests.blocks.TryGeneric
Super Class : java.lang.Object
Implemented Interfaces:

Version: 50.0
JVM supported: 1.6 and greater

Access Flags: 33 ( PUBLIC  SUPER )

Attributes:
@SourceFile: TryGeneric.java

Fields:

Methods:
<init> : () : void
{
    Access Flags: 1 ( PUBLIC )

    Attributes:
    CODE
       (
        Max stack = 1
        Max locals = 1
        Attributes:
            @LineNumberTable:
                0: line 9
                4: line 10
            @LocalVariableTable: 
                0+5: this (Lru/andrew/jclazz/apps/tester/tests/blocks/TryGeneric;), 0
        Exceptions:
       )
    {
        0 aload_0
        1 invokespecial <init>
        4 return
    }
}

test1 : () : void
{
    Access Flags: 1 ( PUBLIC )

    Attributes:
    CODE
       (
        Max stack = 2
        Max locals = 3
        Attributes:
            @LineNumberTable:
                0: line 14
                8: line 17
                16: line 33
                24: line 34
                32: line 35
                40: line 36
                48: line 37
                56: line 38
                64: line 39
                72: line 40
                75: line 19
                76: line 21
                84: line 33
                92: line 34
                100: line 35
                108: line 36
                116: line 37
                124: line 38
                132: line 39
                140: line 40
                143: line 23
                144: line 25
                152: line 33
                160: line 34
                168: line 35
                176: line 36
                184: line 37
                192: line 38
                200: line 39
                208: line 40
                211: line 27
                212: line 29
                220: line 33
                228: line 34
                236: line 35
                244: line 36
                252: line 37
                260: line 38
                268: line 39
                276: line 40
                279: line 33
                288: line 34
                296: line 35
                304: line 36
                312: line 37
                320: line 38
                328: line 39
                338: line 41
                346: line 42
            @LocalVariableTable: 
                76+8: e (Ljava/lang/Exception;), 1
                144+8: err (Ljava/lang/Error;), 1
                212+8: t (Ljava/lang/Throwable;), 1
                0+347: this (Lru/andrew/jclazz/apps/tester/tests/blocks/TryGeneric;), 0
            @StackMapTable: 
                SameLocals1StackItemFrameExtended (+75): stack item = Object(java.lang.Exception)
                SameLocals1StackItemFrameExtended (+67): stack item = Object(java.lang.Error)
                SameLocals1StackItemFrameExtended (+67): stack item = Object(java.lang.Throwable)
                SameLocals1StackItemFrameExtended (+67): stack item = Object(java.lang.Throwable)
                SameFrame (+58): 
            
        Exceptions:
            [8-16): 75 - java.lang.Exception
            [8-16): 143 - java.lang.Error
            [8-16): 211 - java.lang.Throwable
            [8-16): 279
            [75-84): 279
            [143-152): 279
            [211-220): 279
            [279-280): 279
       )
    {
        0 getstatic java.lang.System.out
        3 ldc "Before try" (java.lang.String)
        5 invokevirtual println
        8 getstatic java.lang.System.out
        11 ldc "TRY BLOCK" (java.lang.String)
        13 invokevirtual println
        16 getstatic java.lang.System.out
        19 ldc "." (java.lang.String)
        21 invokevirtual println
        24 getstatic java.lang.System.out
        27 ldc ".." (java.lang.String)
        29 invokevirtual println
        32 getstatic java.lang.System.out
        35 ldc "..." (java.lang.String)
        37 invokevirtual println
        40 getstatic java.lang.System.out
        43 ldc "FINALLY BLOCK" (java.lang.String)
        45 invokevirtual println
        48 getstatic java.lang.System.out
        51 ldc "..." (java.lang.String)
        53 invokevirtual println
        56 getstatic java.lang.System.out
        59 ldc ".." (java.lang.String)
        61 invokevirtual println
        64 getstatic java.lang.System.out
        67 ldc "." (java.lang.String)
        69 invokevirtual println
        72 goto 338
        75 astore_1
        76 getstatic java.lang.System.out
        79 ldc "CATCH BLOCK 1" (java.lang.String)
        81 invokevirtual println
        84 getstatic java.lang.System.out
        87 ldc "." (java.lang.String)
        89 invokevirtual println
        92 getstatic java.lang.System.out
        95 ldc ".." (java.lang.String)
        97 invokevirtual println
        100 getstatic java.lang.System.out
        103 ldc "..." (java.lang.String)
        105 invokevirtual println
        108 getstatic java.lang.System.out
        111 ldc "FINALLY BLOCK" (java.lang.String)
        113 invokevirtual println
        116 getstatic java.lang.System.out
        119 ldc "..." (java.lang.String)
        121 invokevirtual println
        124 getstatic java.lang.System.out
        127 ldc ".." (java.lang.String)
        129 invokevirtual println
        132 getstatic java.lang.System.out
        135 ldc "." (java.lang.String)
        137 invokevirtual println
        140 goto 338
        143 astore_1
        144 getstatic java.lang.System.out
        147 ldc "CATCH BLOCK 2" (java.lang.String)
        149 invokevirtual println
        152 getstatic java.lang.System.out
        155 ldc "." (java.lang.String)
        157 invokevirtual println
        160 getstatic java.lang.System.out
        163 ldc ".." (java.lang.String)
        165 invokevirtual println
        168 getstatic java.lang.System.out
        171 ldc "..." (java.lang.String)
        173 invokevirtual println
        176 getstatic java.lang.System.out
        179 ldc "FINALLY BLOCK" (java.lang.String)
        181 invokevirtual println
        184 getstatic java.lang.System.out
        187 ldc "..." (java.lang.String)
        189 invokevirtual println
        192 getstatic java.lang.System.out
        195 ldc ".." (java.lang.String)
        197 invokevirtual println
        200 getstatic java.lang.System.out
        203 ldc "." (java.lang.String)
        205 invokevirtual println
        208 goto 338
        211 astore_1
        212 getstatic java.lang.System.out
        215 ldc "CATCH BLOCK 3" (java.lang.String)
        217 invokevirtual println
        220 getstatic java.lang.System.out
        223 ldc "." (java.lang.String)
        225 invokevirtual println
        228 getstatic java.lang.System.out
        231 ldc ".." (java.lang.String)
        233 invokevirtual println
        236 getstatic java.lang.System.out
        239 ldc "..." (java.lang.String)
        241 invokevirtual println
        244 getstatic java.lang.System.out
        247 ldc "FINALLY BLOCK" (java.lang.String)
        249 invokevirtual println
        252 getstatic java.lang.System.out
        255 ldc "..." (java.lang.String)
        257 invokevirtual println
        260 getstatic java.lang.System.out
        263 ldc ".." (java.lang.String)
        265 invokevirtual println
        268 getstatic java.lang.System.out
        271 ldc "." (java.lang.String)
        273 invokevirtual println
        276 goto 338
        279 astore_2
        280 getstatic java.lang.System.out
        283 ldc "." (java.lang.String)
        285 invokevirtual println
        288 getstatic java.lang.System.out
        291 ldc ".." (java.lang.String)
        293 invokevirtual println
        296 getstatic java.lang.System.out
        299 ldc "..." (java.lang.String)
        301 invokevirtual println
        304 getstatic java.lang.System.out
        307 ldc "FINALLY BLOCK" (java.lang.String)
        309 invokevirtual println
        312 getstatic java.lang.System.out
        315 ldc "..." (java.lang.String)
        317 invokevirtual println
        320 getstatic java.lang.System.out
        323 ldc ".." (java.lang.String)
        325 invokevirtual println
        328 getstatic java.lang.System.out
        331 ldc "." (java.lang.String)
        333 invokevirtual println
        336 aload_2
        337 athrow
        338 getstatic java.lang.System.out
        341 ldc "After try" (java.lang.String)
        343 invokevirtual println
        346 return
    }
}

test2 : () : void
{
    Access Flags: 1 ( PUBLIC )

    Attributes:
    CODE
       (
        Max stack = 2
        Max locals = 3
        Attributes:
            @LineNumberTable:
                0: line 46
                8: line 49
                16: line 52
                24: line 61
                27: line 54
                28: line 56
                36: line 61
                39: line 58
                40: line 60
                48: line 62
                56: line 79
                64: line 80
                72: line 81
                80: line 82
                88: line 83
                96: line 84
                104: line 85
                112: line 86
                115: line 64
                116: line 66
                124: line 67
                132: line 69
                133: line 71
                141: line 79
                149: line 80
                157: line 81
                165: line 82
                173: line 83
                181: line 84
                189: line 85
                197: line 86
                200: line 73
                201: line 75
                209: line 79
                217: line 80
                225: line 81
                233: line 82
                241: line 83
                249: line 84
                257: line 85
                265: line 86
                268: line 79
                277: line 80
                285: line 81
                293: line 82
                301: line 83
                309: line 84
                317: line 85
                327: line 87
                335: line 88
            @LocalVariableTable: 
                28+8: ee (Ljava/lang/Exception;), 1
                40+8: tt (Ljava/lang/Throwable;), 1
                116+16: e (Ljava/lang/Exception;), 1
                133+8: err (Ljava/lang/Error;), 1
                201+8: t (Ljava/lang/Throwable;), 1
                0+336: this (Lru/andrew/jclazz/apps/tester/tests/blocks/TryGeneric;), 0
            @StackMapTable: 
                SameLocals1StackItemFrame (+27): stack item = Object(java.lang.Exception)
                SameLocals1StackItemFrame (+11): stack item = Object(java.lang.Throwable)
                SameFrame (+8): 
                SameLocals1StackItemFrameExtended (+66): stack item = Object(java.lang.Exception)
                SameLocals1StackItemFrame (+16): stack item = Object(java.lang.Error)
                SameLocals1StackItemFrameExtended (+67): stack item = Object(java.lang.Throwable)
                SameLocals1StackItemFrameExtended (+67): stack item = Object(java.lang.Throwable)
                SameFrame (+58): 
            
        Exceptions:
            [16-24): 27 - java.lang.Exception
            [16-24): 39 - java.lang.Throwable
            [8-56): 115 - java.lang.Exception
            [8-56): 132 - java.lang.Error
            [8-56): 200 - java.lang.Throwable
            [8-56): 268
            [115-141): 268
            [200-209): 268
            [268-269): 268
       )
    {
        0 getstatic java.lang.System.out
        3 ldc "Before try" (java.lang.String)
        5 invokevirtual println
        8 getstatic java.lang.System.out
        11 ldc "TRY BLOCK start" (java.lang.String)
        13 invokevirtual println
        16 getstatic java.lang.System.out
        19 ldc "INNER TRY BLOCK" (java.lang.String)
        21 invokevirtual println
        24 goto 48
        27 astore_1
        28 getstatic java.lang.System.out
        31 ldc "INNER CATCH BLOCK 1" (java.lang.String)
        33 invokevirtual println
        36 goto 48
        39 astore_1
        40 getstatic java.lang.System.out
        43 ldc "INNER CATCH BLOCK 2" (java.lang.String)
        45 invokevirtual println
        48 getstatic java.lang.System.out
        51 ldc "TRY BLOCK end" (java.lang.String)
        53 invokevirtual println
        56 getstatic java.lang.System.out
        59 ldc "." (java.lang.String)
        61 invokevirtual println
        64 getstatic java.lang.System.out
        67 ldc ".." (java.lang.String)
        69 invokevirtual println
        72 getstatic java.lang.System.out
        75 ldc "..." (java.lang.String)
        77 invokevirtual println
        80 getstatic java.lang.System.out
        83 ldc "FINALLY BLOCK" (java.lang.String)
        85 invokevirtual println
        88 getstatic java.lang.System.out
        91 ldc "..." (java.lang.String)
        93 invokevirtual println
        96 getstatic java.lang.System.out
        99 ldc ".." (java.lang.String)
        101 invokevirtual println
        104 getstatic java.lang.System.out
        107 ldc "." (java.lang.String)
        109 invokevirtual println
        112 goto 327
        115 astore_1
        116 getstatic java.lang.System.out
        119 ldc "CATCH BLOCK 1" (java.lang.String)
        121 invokevirtual println
        124 new java.lang.RuntimeException
        127 dup
        128 invokespecial <init>
        131 athrow
        132 astore_1
        133 getstatic java.lang.System.out
        136 ldc "CATCH BLOCK 2" (java.lang.String)
        138 invokevirtual println
        141 getstatic java.lang.System.out
        144 ldc "." (java.lang.String)
        146 invokevirtual println
        149 getstatic java.lang.System.out
        152 ldc ".." (java.lang.String)
        154 invokevirtual println
        157 getstatic java.lang.System.out
        160 ldc "..." (java.lang.String)
        162 invokevirtual println
        165 getstatic java.lang.System.out
        168 ldc "FINALLY BLOCK" (java.lang.String)
        170 invokevirtual println
        173 getstatic java.lang.System.out
        176 ldc "..." (java.lang.String)
        178 invokevirtual println
        181 getstatic java.lang.System.out
        184 ldc ".." (java.lang.String)
        186 invokevirtual println
        189 getstatic java.lang.System.out
        192 ldc "." (java.lang.String)
        194 invokevirtual println
        197 goto 327
        200 astore_1
        201 getstatic java.lang.System.out
        204 ldc "CATCH BLOCK 3" (java.lang.String)
        206 invokevirtual println
        209 getstatic java.lang.System.out
        212 ldc "." (java.lang.String)
        214 invokevirtual println
        217 getstatic java.lang.System.out
        220 ldc ".." (java.lang.String)
        222 invokevirtual println
        225 getstatic java.lang.System.out
        228 ldc "..." (java.lang.String)
        230 invokevirtual println
        233 getstatic java.lang.System.out
        236 ldc "FINALLY BLOCK" (java.lang.String)
        238 invokevirtual println
        241 getstatic java.lang.System.out
        244 ldc "..." (java.lang.String)
        246 invokevirtual println
        249 getstatic java.lang.System.out
        252 ldc ".." (java.lang.String)
        254 invokevirtual println
        257 getstatic java.lang.System.out
        260 ldc "." (java.lang.String)
        262 invokevirtual println
        265 goto 327
        268 astore_2
        269 getstatic java.lang.System.out
        272 ldc "." (java.lang.String)
        274 invokevirtual println
        277 getstatic java.lang.System.out
        280 ldc ".." (java.lang.String)
        282 invokevirtual println
        285 getstatic java.lang.System.out
        288 ldc "..." (java.lang.String)
        290 invokevirtual println
        293 getstatic java.lang.System.out
        296 ldc "FINALLY BLOCK" (java.lang.String)
        298 invokevirtual println
        301 getstatic java.lang.System.out
        304 ldc "..." (java.lang.String)
        306 invokevirtual println
        309 getstatic java.lang.System.out
        312 ldc ".." (java.lang.String)
        314 invokevirtual println
        317 getstatic java.lang.System.out
        320 ldc "." (java.lang.String)
        322 invokevirtual println
        325 aload_2
        326 athrow
        327 getstatic java.lang.System.out
        330 ldc "After try" (java.lang.String)
        332 invokevirtual println
        335 return
    }
}

test3 : (java.lang.String) : void
{
    Access Flags: 1 ( PUBLIC )

    Attributes:
    CODE
       (
        Max stack = 2
        Max locals = 3
        Attributes:
            @LineNumberTable:
                0: line 94
                9: line 96
                10: line 98
                18: line 102
                21: line 100
                22: line 103
            @LocalVariableTable: 
                22+0: e (Ljava/lang/Exception;), 2
                0+23: this (Lru/andrew/jclazz/apps/tester/tests/blocks/TryGeneric;), 0
                0+23: style (Ljava/lang/String;), 1
            @StackMapTable: 
                SameFrame (+10): 
                SameLocals1StackItemFrame (+10): stack item = Object(java.lang.Exception)
                SameFrame (+0): 
            
        Exceptions:
            [0-9): 21 - java.lang.Exception
            [10-18): 21 - java.lang.Exception
       )
    {
        0 ldc "" (java.lang.String)
        2 aload_1
        3 invokevirtual equals
        6 ifeq 10
        9 return
        10 getstatic java.lang.System.out
        13 ldc "SOUT" (java.lang.String)
        15 invokevirtual println
        18 goto 22
        21 astore_2
        22 return
    }
}

test4 : (java.lang.String) : void
{
    Access Flags: 1 ( PUBLIC )

    Attributes:
    CODE
       (
        Max stack = 2
        Max locals = 4
        Attributes:
            @LineNumberTable:
                0: line 109
                9: line 121
                18: line 113
                26: line 121
                34: line 122
                37: line 115
                38: line 117
                46: line 121
                54: line 122
                57: line 121
                68: line 123
            @LocalVariableTable: 
                38+8: e (Ljava/lang/Exception;), 2
                0+69: this (Lru/andrew/jclazz/apps/tester/tests/blocks/TryGeneric;), 0
                0+69: style (Ljava/lang/String;), 1
            @StackMapTable: 
                SameFrame (+18): 
                SameLocals1StackItemFrame (+18): stack item = Object(java.lang.Exception)
                SameLocals1StackItemFrame (+19): stack item = Object(java.lang.Throwable)
                SameFrame (+10): 
            
        Exceptions:
            [0-9): 37 - java.lang.Exception
            [18-26): 37 - java.lang.Exception
            [0-9): 57
            [18-26): 57
            [37-46): 57
            [57-58): 57
       )
    {
        0 ldc "" (java.lang.String)
        2 aload_1
        3 invokevirtual equals
        6 ifeq 18
        9 getstatic java.lang.System.out
        12 ldc "FINALLY" (java.lang.String)
        14 invokevirtual println
        17 return
        18 getstatic java.lang.System.out
        21 ldc "SOUT" (java.lang.String)
        23 invokevirtual println
        26 getstatic java.lang.System.out
        29 ldc "FINALLY" (java.lang.String)
        31 invokevirtual println
        34 goto 68
        37 astore_2
        38 getstatic java.lang.System.out
        41 ldc "EXCEPTION" (java.lang.String)
        43 invokevirtual println
        46 getstatic java.lang.System.out
        49 ldc "FINALLY" (java.lang.String)
        51 invokevirtual println
        54 goto 68
        57 astore_3
        58 getstatic java.lang.System.out
        61 ldc "FINALLY" (java.lang.String)
        63 invokevirtual println
        66 aload_3
        67 athrow
        68 return
    }
}

test5 : (java.lang.String) : void
{
    Access Flags: 1 ( PUBLIC )

    Attributes:
    CODE
       (
        Max stack = 2
        Max locals = 4
        Attributes:
            @LineNumberTable:
                0: line 129
                9: line 131
                17: line 133
                25: line 141
                33: line 142
                36: line 135
                37: line 137
                45: line 141
                53: line 142
                56: line 141
                67: line 143
            @LocalVariableTable: 
                37+8: e (Ljava/lang/Exception;), 2
                0+68: this (Lru/andrew/jclazz/apps/tester/tests/blocks/TryGeneric;), 0
                0+68: style (Ljava/lang/String;), 1
            @StackMapTable: 
                SameFrame (+17): 
                SameLocals1StackItemFrame (+18): stack item = Object(java.lang.Exception)
                SameLocals1StackItemFrame (+19): stack item = Object(java.lang.Throwable)
                SameFrame (+10): 
            
        Exceptions:
            [0-25): 36 - java.lang.Exception
            [0-25): 56
            [36-45): 56
            [56-57): 56
       )
    {
        0 ldc "" (java.lang.String)
        2 aload_1
        3 invokevirtual equals
        6 ifeq 17
        9 new java.lang.RuntimeException
        12 dup
        13 invokespecial <init>
        16 athrow
        17 getstatic java.lang.System.out
        20 ldc "SOUT" (java.lang.String)
        22 invokevirtual println
        25 getstatic java.lang.System.out
        28 ldc "FINALLY" (java.lang.String)
        30 invokevirtual println
        33 goto 67
        36 astore_2
        37 getstatic java.lang.System.out
        40 ldc "EXCEPTION" (java.lang.String)
        42 invokevirtual println
        45 getstatic java.lang.System.out
        48 ldc "FINALLY" (java.lang.String)
        50 invokevirtual println
        53 goto 67
        56 astore_3
        57 getstatic java.lang.System.out
        60 ldc "FINALLY" (java.lang.String)
        62 invokevirtual println
        65 aload_3
        66 athrow
        67 return
    }
}

test6 : (java.lang.String) : void
{
    Access Flags: 1 ( PUBLIC )

    Attributes:
    @Exceptions: 
            java.lang.Throwable
    CODE
       (
        Max stack = 2
        Max locals = 4
        Attributes:
            @LineNumberTable:
                0: line 149
                9: line 151
                17: line 153
                25: line 161
                33: line 162
                36: line 155
                37: line 157
                45: line 161
                53: line 162
                56: line 161
                67: line 163
            @LocalVariableTable: 
                37+8: e (Ljava/lang/Exception;), 2
                0+68: this (Lru/andrew/jclazz/apps/tester/tests/blocks/TryGeneric;), 0
                0+68: style (Ljava/lang/String;), 1
            @StackMapTable: 
                SameFrame (+17): 
                SameLocals1StackItemFrame (+18): stack item = Object(java.lang.Exception)
                SameLocals1StackItemFrame (+19): stack item = Object(java.lang.Throwable)
                SameFrame (+10): 
            
        Exceptions:
            [0-25): 36 - java.lang.Exception
            [0-25): 56
            [36-45): 56
            [56-57): 56
       )
    {
        0 ldc "" (java.lang.String)
        2 aload_1
        3 invokevirtual equals
        6 ifeq 17
        9 new java.lang.Throwable
        12 dup
        13 invokespecial <init>
        16 athrow
        17 getstatic java.lang.System.out
        20 ldc "SOUT" (java.lang.String)
        22 invokevirtual println
        25 getstatic java.lang.System.out
        28 ldc "FINALLY" (java.lang.String)
        30 invokevirtual println
        33 goto 67
        36 astore_2
        37 getstatic java.lang.System.out
        40 ldc "EXCEPTION" (java.lang.String)
        42 invokevirtual println
        45 getstatic java.lang.System.out
        48 ldc "FINALLY" (java.lang.String)
        50 invokevirtual println
        53 goto 67
        56 astore_3
        57 getstatic java.lang.System.out
        60 ldc "FINALLY" (java.lang.String)
        62 invokevirtual println
        65 aload_3
        66 athrow
        67 return
    }
}

test7 : () : void
{
    Access Flags: 1 ( PUBLIC )

    Attributes:
    @Exceptions: 
            java.lang.Throwable
    CODE
       (
        Max stack = 3
        Max locals = 3
        Attributes:
            @LineNumberTable:
                0: line 167
                9: line 172
                22: line 175
                23: line 181
                26: line 178
                27: line 180
                29: line 182
                37: line 183
            @LocalVariableTable: 
                23+0: eofexception (Ljava/io/EOFException;), 2
                27+2: throwable (Ljava/lang/Throwable;), 2
                0+38: this (Lru/andrew/jclazz/apps/tester/tests/blocks/TryGeneric;), 0
                9+29: datainputstream (Ljava/io/DataInputStream;), 1
            @StackMapTable: 
                AppendFrame (+9): additional locals - Object(java.io.DataInputStream)
                SameLocals1StackItemFrame (+12): stack item = Object(java.io.EOFException)
                SameLocals1StackItemFrame (+3): stack item = Object(java.lang.Throwable)
                SameFrame (+2): 
            
        Exceptions:
            [9-22): 22 - java.io.EOFException
            [9-22): 26 - java.lang.Throwable
       )
    {
        0 new java.io.DataInputStream
        3 dup
        4 aconst_null
        5 invokespecial <init>
        8 astore_1
        9 getstatic java.lang.System.out
        12 aload_1
        13 invokevirtual readUTF
        16 invokevirtual println
        19 goto 9
        22 astore_2
        23 goto 29
        26 astore_2
        27 aload_2
        28 athrow
        29 getstatic java.lang.System.out
        32 ldc "1" (java.lang.String)
        34 invokevirtual println
        37 return
    }
}

test8 : () : void
{
    Access Flags: 1 ( PUBLIC )

    Attributes:
    CODE
       (
        Max stack = 3
        Max locals = 4
        Attributes:
            @LineNumberTable:
                0: line 189
                8: line 199
                16: line 204
                19: line 201
                20: line 203
                45: line 205
                48: line 191
                49: line 193
                53: line 199
                61: line 204
                64: line 201
                65: line 203
                90: line 205
                93: line 197
                94: line 199
                102: line 204
                105: line 201
                106: line 203
                131: line 204
                133: line 206
            @LocalVariableTable: 
                20+25: ex2 (Ljava/lang/Exception;), 1
                49+4: ex (Ljava/lang/Exception;), 1
                65+25: ex2 (Ljava/lang/Exception;), 1
                106+25: ex2 (Ljava/lang/Exception;), 3
                0+134: this (Lru/andrew/jclazz/apps/tester/tests/blocks/TryGeneric;), 0
            @StackMapTable: 
                SameLocals1StackItemFrame (+19): stack item = Object(java.lang.Exception)
                SameLocals1StackItemFrame (+28): stack item = Object(java.lang.Exception)
                SameLocals1StackItemFrame (+15): stack item = Object(java.lang.Exception)
                SameLocals1StackItemFrame (+28): stack item = Object(java.lang.Throwable)
                FullFrame (+11): locals - Object(ru.andrew.jclazz.apps.tester.tests.blocks.TryGeneric) Top Object(java.lang.Throwable), stack - Object(java.lang.Exception)
                SameFrame (+25): 
                ChopFrame (+1): 2 last absent locals
            
        Exceptions:
            [8-16): 19 - java.lang.Exception
            [0-8): 48 - java.lang.Exception
            [53-61): 64 - java.lang.Exception
            [0-8): 93
            [48-53): 93
            [94-102): 105 - java.lang.Exception
            [93-94): 93
       )
    {
        0 getstatic java.lang.System.out
        3 ldc "TRY" (java.lang.String)
        5 invokevirtual println
        8 getstatic java.lang.System.out
        11 ldc "FINALLY TRY" (java.lang.String)
        13 invokevirtual println
        16 goto 133
        19 astore_1
        20 getstatic java.lang.System.out
        23 new java.lang.StringBuilder
        26 dup
        27 invokespecial <init>
        30 ldc "EX2" (java.lang.String)
        32 invokevirtual append
        35 aload_1
        36 invokevirtual append
        39 invokevirtual toString
        42 invokevirtual println
        45 goto 133
        48 astore_1
        49 aload_1
        50 invokevirtual printStackTrace
        53 getstatic java.lang.System.out
        56 ldc "FINALLY TRY" (java.lang.String)
        58 invokevirtual println
        61 goto 133
        64 astore_1
        65 getstatic java.lang.System.out
        68 new java.lang.StringBuilder
        71 dup
        72 invokespecial <init>
        75 ldc "EX2" (java.lang.String)
        77 invokevirtual append
        80 aload_1
        81 invokevirtual append
        84 invokevirtual toString
        87 invokevirtual println
        90 goto 133
        93 astore_2
        94 getstatic java.lang.System.out
        97 ldc "FINALLY TRY" (java.lang.String)
        99 invokevirtual println
        102 goto 131
        105 astore_3
        106 getstatic java.lang.System.out
        109 new java.lang.StringBuilder
        112 dup
        113 invokespecial <init>
        116 ldc "EX2" (java.lang.String)
        118 invokevirtual append
        121 aload_3
        122 invokevirtual append
        125 invokevirtual toString
        128 invokevirtual println
        131 aload_2
        132 athrow
        133 return
    }
}

Constant Pool:
0: 
1: Methodref: java.lang.Object.<init> (()V)
2: Fieldref: java.io.PrintStream
3: String: "Before try"
4: Methodref: java.io.PrintStream.println ((Ljava/lang/String;)V)
5: String: "TRY BLOCK"
6: String: "."
7: String: ".."
8: String: "..."
9: String: "FINALLY BLOCK"
10: Class: java.lang.Exception
11: String: "CATCH BLOCK 1"
12: Class: java.lang.Error
13: String: "CATCH BLOCK 2"
14: Class: java.lang.Throwable
15: String: "CATCH BLOCK 3"
16: String: "After try"
17: String: "TRY BLOCK start"
18: String: "INNER TRY BLOCK"
19: String: "INNER CATCH BLOCK 1"
20: String: "INNER CATCH BLOCK 2"
21: String: "TRY BLOCK end"
22: Class: java.lang.RuntimeException
23: Methodref: java.lang.RuntimeException.<init> (()V)
24: String: ""
25: Methodref: java.lang.String.equals ((Ljava/lang/Object;)Z)
26: String: "SOUT"
27: String: "FINALLY"
28: String: "EXCEPTION"
29: Methodref: java.lang.Throwable.<init> (()V)
30: Class: java.io.DataInputStream
31: Methodref: java.io.DataInputStream.<init> ((Ljava/io/InputStream;)V)
32: Methodref: java.io.DataInputStream.readUTF (()Ljava/lang/String;)
33: Class: java.io.EOFException
34: String: "1"
35: String: "TRY"
36: String: "FINALLY TRY"
37: Class: java.lang.StringBuilder
38: Methodref: java.lang.StringBuilder.<init> (()V)
39: String: "EX2"
40: Methodref: java.lang.StringBuilder.append ((Ljava/lang/String;)Ljava/lang/StringBuilder;)
41: Methodref: java.lang.StringBuilder.append ((Ljava/lang/Object;)Ljava/lang/StringBuilder;)
42: Methodref: java.lang.StringBuilder.toString (()Ljava/lang/String;)
43: Methodref: java.lang.Exception.printStackTrace (()V)
44: Class: ru.andrew.jclazz.apps.tester.tests.blocks.TryGeneric
45: Class: java.lang.Object
46: Utf8: <init>
47: Utf8: ()V
48: Utf8: Code
49: Utf8: LineNumberTable
50: Utf8: LocalVariableTable
51: Utf8: this
52: Utf8: Lru/andrew/jclazz/apps/tester/tests/blocks/TryGeneric;
53: Utf8: test1
54: Utf8: e
55: Utf8: Ljava/lang/Exception;
56: Utf8: err
57: Utf8: Ljava/lang/Error;
58: Utf8: t
59: Utf8: Ljava/lang/Throwable;
60: Utf8: StackMapTable
61: Class: java.lang.Exception
62: Class: java.lang.Error
63: Class: java.lang.Throwable
64: Utf8: test2
65: Utf8: ee
66: Utf8: tt
67: Utf8: test3
68: Utf8: (Ljava/lang/String;)V
69: Utf8: style
70: Utf8: Ljava/lang/String;
71: Utf8: test4
72: Utf8: test5
73: Utf8: test6
74: Utf8: Exceptions
75: Utf8: test7
76: Utf8: eofexception
77: Utf8: Ljava/io/EOFException;
78: Utf8: throwable
79: Utf8: datainputstream
80: Utf8: Ljava/io/DataInputStream;
81: Class: java.io.DataInputStream
82: Class: java.io.EOFException
83: Utf8: test8
84: Utf8: ex2
85: Utf8: ex
86: Class: ru.andrew.jclazz.apps.tester.tests.blocks.TryGeneric
87: Class: java.lang.Throwable
88: Utf8: SourceFile
89: Utf8: TryGeneric.java
90: NameAndType: <init> (()V)
91: Class: java.lang.System
92: NameAndType: out (Ljava/io/PrintStream;)
93: Utf8: Before try
94: Class: java.io.PrintStream
95: NameAndType: println ((Ljava/lang/String;)V)
96: Utf8: TRY BLOCK
97: Utf8: .
98: Utf8: ..
99: Utf8: ...
100: Utf8: FINALLY BLOCK
101: Utf8: java/lang/Exception
102: Utf8: CATCH BLOCK 1
103: Utf8: java/lang/Error
104: Utf8: CATCH BLOCK 2
105: Utf8: java/lang/Throwable
106: Utf8: CATCH BLOCK 3
107: Utf8: After try
108: Utf8: TRY BLOCK start
109: Utf8: INNER TRY BLOCK
110: Utf8: INNER CATCH BLOCK 1
111: Utf8: INNER CATCH BLOCK 2
112: Utf8: TRY BLOCK end
113: Utf8: java/lang/RuntimeException
114: Utf8: 
115: Class: java.lang.String
116: NameAndType: equals ((Ljava/lang/Object;)Z)
117: Utf8: SOUT
118: Utf8: FINALLY
119: Utf8: EXCEPTION
120: Utf8: java/io/DataInputStream
121: NameAndType: <init> ((Ljava/io/InputStream;)V)
122: NameAndType: readUTF (()Ljava/lang/String;)
123: Utf8: java/io/EOFException
124: Utf8: 1
125: Utf8: TRY
126: Utf8: FINALLY TRY
127: Utf8: java/lang/StringBuilder
128: Utf8: EX2
129: NameAndType: append ((Ljava/lang/String;)Ljava/lang/StringBuilder;)
130: NameAndType: append ((Ljava/lang/Object;)Ljava/lang/StringBuilder;)
131: NameAndType: toString (()Ljava/lang/String;)
132: NameAndType: printStackTrace (()V)
133: Utf8: ru/andrew/jclazz/apps/tester/tests/blocks/TryGeneric
134: Utf8: java/lang/Object
135: Utf8: java/lang/System
136: Utf8: out
137: Utf8: Ljava/io/PrintStream;
138: Utf8: java/io/PrintStream
139: Utf8: println
140: Utf8: java/lang/String
141: Utf8: equals
142: Utf8: (Ljava/lang/Object;)Z
143: Utf8: (Ljava/io/InputStream;)V
144: Utf8: readUTF
145: Utf8: ()Ljava/lang/String;
146: Utf8: append
147: Utf8: (Ljava/lang/String;)Ljava/lang/StringBuilder;
148: Utf8: (Ljava/lang/Object;)Ljava/lang/StringBuilder;
149: Utf8: toString
150: Utf8: printStackTrace
