This Class  : ru.andrew.jclazz.apps.tester.tests.clazz.AnonymousClazz01$1
Super Class : java.lang.Object
Implemented Interfaces:
   java.util.Comparator

Version: 50.0
JVM supported: 1.6 and greater

Access Flags: 0 ()

Attributes:
@SourceFile: AnonymousClazz01.java
@EnclosingMethod: 
    Enclosing class: ru.andrew.jclazz.apps.tester.tests.clazz.AnonymousClazz01
    Enclosing method: test ((Ljava/util/List;)V)
@InnerClasses: 
    * Inner class - ru.andrew.jclazz.apps.tester.tests.clazz.AnonymousClazz01$1
      Outer class - 
      Inner name - 
      Inner class access flags - 0

Fields:
this$0 : ru.andrew.jclazz.apps.tester.tests.clazz.AnonymousClazz01
{
    Access Flags: 4112 ( FINAL  SYNTHETIC )

    Attributes:
}


Methods:
<init> : (ru.andrew.jclazz.apps.tester.tests.clazz.AnonymousClazz01) : void
{
    Access Flags: 0 ()

    Attributes:
    CODE
       (
        Max stack = 2
        Max locals = 2
        Attributes:
            @LineNumberTable:
                0: line 19
            @LocalVariableTable: 
                0+10: this (Lru/andrew/jclazz/apps/tester/tests/clazz/AnonymousClazz01$1;), 0
        Exceptions:
       )
    {
        0 aload_0
        1 aload_1
        2 putfield this$0
        5 aload_0
        6 invokespecial <init>
        9 return
    }
}

compare : (java.lang.Object, java.lang.Object) : int
{
    Access Flags: 1 ( PUBLIC )

    Attributes:
    CODE
       (
        Max stack = 4
        Max locals = 3
        Attributes:
            @LineNumberTable:
                0: line 23
                12: line 25
                34: line 27
                49: line 29
                51: line 33
            @LocalVariableTable: 
                0+53: this (Lru/andrew/jclazz/apps/tester/tests/clazz/AnonymousClazz01$1;), 0
                0+53: o1 (Ljava/lang/Object;), 1
                0+53: o2 (Ljava/lang/Object;), 2
            @StackMapTable: 
                SameFrame (+51): 
            
        Exceptions:
       )
    {
        0 aload_0
        1 getfield this$0
        4 invokestatic ru.andrew.jclazz.apps.tester.tests.clazz.AnonymousClazz01.access$000
        7 bipush 12 (int)
        9 if_icmpne 51
        12 aload_0
        13 getfield this$0
        16 invokestatic ru.andrew.jclazz.apps.tester.tests.clazz.AnonymousClazz01.access$100
        19 new java.math.BigInteger
        22 dup
        23 ldc "1234" (java.lang.String)
        25 invokespecial <init>
        28 invokevirtual equals
        31 ifeq 51
        34 aload_0
        35 getfield this$0
        38 invokestatic ru.andrew.jclazz.apps.tester.tests.clazz.AnonymousClazz01.access$200
        41 ldc "123" (java.lang.String)
        43 invokevirtual equals
        46 ifeq 51
        49 iconst_1
        50 ireturn
        51 iconst_0
        52 ireturn
    }
}

Constant Pool:
0: 
1: Fieldref: ru.andrew.jclazz.apps.tester.tests.clazz.AnonymousClazz01
2: Methodref: java.lang.Object.<init> (()V)
3: Methodref: ru.andrew.jclazz.apps.tester.tests.clazz.AnonymousClazz01.access$000 ((Lru/andrew/jclazz/apps/tester/tests/clazz/AnonymousClazz01;)I)
4: Methodref: ru.andrew.jclazz.apps.tester.tests.clazz.AnonymousClazz01.access$100 ((Lru/andrew/jclazz/apps/tester/tests/clazz/AnonymousClazz01;)Ljava/math/BigInteger;)
5: Class: java.math.BigInteger
6: String: "1234"
7: Methodref: java.math.BigInteger.<init> ((Ljava/lang/String;)V)
8: Methodref: java.math.BigInteger.equals ((Ljava/lang/Object;)Z)
9: Methodref: ru.andrew.jclazz.apps.tester.tests.clazz.AnonymousClazz01.access$200 ((Lru/andrew/jclazz/apps/tester/tests/clazz/AnonymousClazz01;)Ljava/lang/String;)
10: String: "123"
11: Methodref: java.lang.String.equals ((Ljava/lang/Object;)Z)
12: Class: ru.andrew.jclazz.apps.tester.tests.clazz.AnonymousClazz01$1
13: Class: java.lang.Object
14: Class: java.util.Comparator
15: Utf8: this$0
16: Utf8: Lru/andrew/jclazz/apps/tester/tests/clazz/AnonymousClazz01;
17: Utf8: <init>
18: Utf8: (Lru/andrew/jclazz/apps/tester/tests/clazz/AnonymousClazz01;)V
19: Utf8: Code
20: Utf8: LineNumberTable
21: Utf8: LocalVariableTable
22: Utf8: this
23: Utf8: 
24: Utf8: InnerClasses
25: Utf8: Lru/andrew/jclazz/apps/tester/tests/clazz/AnonymousClazz01$1;
26: Utf8: compare
27: Utf8: (Ljava/lang/Object;Ljava/lang/Object;)I
28: Utf8: o1
29: Utf8: Ljava/lang/Object;
30: Utf8: o2
31: Utf8: StackMapTable
32: Utf8: SourceFile
33: Utf8: AnonymousClazz01.java
34: Utf8: EnclosingMethod
35: Class: ru.andrew.jclazz.apps.tester.tests.clazz.AnonymousClazz01
36: NameAndType: test ((Ljava/util/List;)V)
37: NameAndType: this$0 (Lru/andrew/jclazz/apps/tester/tests/clazz/AnonymousClazz01;)
38: NameAndType: <init> (()V)
39: NameAndType: access$000 ((Lru/andrew/jclazz/apps/tester/tests/clazz/AnonymousClazz01;)I)
40: NameAndType: access$100 ((Lru/andrew/jclazz/apps/tester/tests/clazz/AnonymousClazz01;)Ljava/math/BigInteger;)
41: Utf8: java/math/BigInteger
42: Utf8: 1234
43: NameAndType: <init> ((Ljava/lang/String;)V)
44: NameAndType: equals ((Ljava/lang/Object;)Z)
45: NameAndType: access$200 ((Lru/andrew/jclazz/apps/tester/tests/clazz/AnonymousClazz01;)Ljava/lang/String;)
46: Utf8: 123
47: Class: java.lang.String
48: Utf8: ru/andrew/jclazz/apps/tester/tests/clazz/AnonymousClazz01$1
49: Utf8: java/lang/Object
50: Utf8: java/util/Comparator
51: Utf8: ru/andrew/jclazz/apps/tester/tests/clazz/AnonymousClazz01
52: Utf8: test
53: Utf8: (Ljava/util/List;)V
54: Utf8: ()V
55: Utf8: access$000
56: Utf8: (Lru/andrew/jclazz/apps/tester/tests/clazz/AnonymousClazz01;)I
57: Utf8: access$100
58: Utf8: (Lru/andrew/jclazz/apps/tester/tests/clazz/AnonymousClazz01;)Ljava/math/BigInteger;
59: Utf8: (Ljava/lang/String;)V
60: Utf8: equals
61: Utf8: (Ljava/lang/Object;)Z
62: Utf8: access$200
63: Utf8: (Lru/andrew/jclazz/apps/tester/tests/clazz/AnonymousClazz01;)Ljava/lang/String;
64: Utf8: java/lang/String
