This Class  : ru.andrew.jclazz.apps.tester.tests.clazz.ClazzEnum2
Super Class : java.lang.Object
Implemented Interfaces:

Version: 50.0
JVM supported: 1.6 and greater

Access Flags: 33 ( PUBLIC  SUPER )

Attributes:
@SourceFile: ClazzEnum2.java
@InnerClasses: 
    * Inner class - ru.andrew.jclazz.apps.tester.tests.clazz.ClazzEnum2$SM_1
      Outer class - ru.andrew.jclazz.apps.tester.tests.clazz.ClazzEnum2
      Inner name - SM_1
      Inner class access flags - 8
    * Inner class - java.awt.Component$BaselineResizeBehavior
      Outer class - java.awt.Component
      Inner name - BaselineResizeBehavior
      Inner class access flags - 16409

Fields:

Methods:
<init> : () : void
{
    Access Flags: 1 ( PUBLIC )

    Attributes:
    CODE
       (
        Max stack = 1
        Max locals = 1
        Attributes:
            @LineNumberTable:
                0: line 9
                4: line 10
            @LocalVariableTable: 
                0+5: this (Lru/andrew/jclazz/apps/tester/tests/clazz/ClazzEnum2;), 0
        Exceptions:
       )
    {
        0 aload_0
        1 invokespecial <init>
        4 return
    }
}

main : () : void
{
    Access Flags: 1 ( PUBLIC )

    Attributes:
    CODE
       (
        Max stack = 2
        Max locals = 2
        Attributes:
            @LineNumberTable:
                0: line 14
                4: line 15
                44: line 18
                52: line 19
                55: line 21
                63: line 22
                66: line 24
                74: line 25
                77: line 27
                85: line 28
                88: line 30
                96: line 32
            @LocalVariableTable: 
                0+97: this (Lru/andrew/jclazz/apps/tester/tests/clazz/ClazzEnum2;), 0
                4+93: os (Ljava/awt/Component$BaselineResizeBehavior;), 1
            @StackMapTable: 
                AppendFrame (+44): additional locals - Object(java.awt.Component$BaselineResizeBehavior)
                SameFrame (+10): 
                SameFrame (+10): 
                SameFrame (+10): 
                SameFrame (+10): 
                SameFrame (+7): 
            
        Exceptions:
       )
    {
        0 getstatic java.awt.Component$BaselineResizeBehavior.CONSTANT_ASCENT
        3 astore_1
        4 getstatic ru.andrew.jclazz.apps.tester.tests.clazz.ClazzEnum2$SM_1.switchMap
        7 aload_1
        8 invokevirtual ordinal
        11 iaload
        12 tableswitch default:88 1:44 2:55 3:66 4:77 
        44 getstatic java.lang.System.out
        47 ldc "You chose Windows!" (java.lang.String)
        49 invokevirtual println
        52 goto 96
        55 getstatic java.lang.System.out
        58 ldc "You chose Unix!" (java.lang.String)
        60 invokevirtual println
        63 goto 96
        66 getstatic java.lang.System.out
        69 ldc "You chose Linux!" (java.lang.String)
        71 invokevirtual println
        74 goto 96
        77 getstatic java.lang.System.out
        80 ldc "You chose Macintosh!" (java.lang.String)
        82 invokevirtual println
        85 goto 96
        88 getstatic java.lang.System.out
        91 ldc "I don't know your OS." (java.lang.String)
        93 invokevirtual println
        96 return
    }
}

Constant Pool:
0: 
1: Methodref: java.lang.Object.<init> (()V)
2: Fieldref: java.awt.Component$BaselineResizeBehavior
3: Fieldref: int[]
4: Methodref: java.awt.Component$BaselineResizeBehavior.ordinal (()I)
5: Fieldref: java.io.PrintStream
6: String: "You chose Windows!"
7: Methodref: java.io.PrintStream.println ((Ljava/lang/String;)V)
8: String: "You chose Unix!"
9: String: "You chose Linux!"
10: String: "You chose Macintosh!"
11: String: "I don't know your OS."
12: Class: ru.andrew.jclazz.apps.tester.tests.clazz.ClazzEnum2
13: Class: java.lang.Object
14: Class: ru.andrew.jclazz.apps.tester.tests.clazz.ClazzEnum2$SM_1
15: Utf8: SM_1
16: Utf8: InnerClasses
17: Utf8: <init>
18: Utf8: ()V
19: Utf8: Code
20: Utf8: LineNumberTable
21: Utf8: LocalVariableTable
22: Utf8: this
23: Utf8: Lru/andrew/jclazz/apps/tester/tests/clazz/ClazzEnum2;
24: Utf8: main
25: Utf8: os
26: Class: java.awt.Component$BaselineResizeBehavior
27: Utf8: BaselineResizeBehavior
28: Utf8: Ljava/awt/Component$BaselineResizeBehavior;
29: Utf8: StackMapTable
30: Class: java.awt.Component$BaselineResizeBehavior
31: Utf8: SourceFile
32: Utf8: ClazzEnum2.java
33: NameAndType: <init> (()V)
34: NameAndType: CONSTANT_ASCENT (Ljava/awt/Component$BaselineResizeBehavior;)
35: NameAndType: switchMap ([I)
36: NameAndType: ordinal (()I)
37: Class: java.lang.System
38: NameAndType: out (Ljava/io/PrintStream;)
39: Utf8: You chose Windows!
40: Class: java.io.PrintStream
41: NameAndType: println ((Ljava/lang/String;)V)
42: Utf8: You chose Unix!
43: Utf8: You chose Linux!
44: Utf8: You chose Macintosh!
45: Utf8: I don't know your OS.
46: Utf8: ru/andrew/jclazz/apps/tester/tests/clazz/ClazzEnum2
47: Utf8: java/lang/Object
48: Utf8: ru/andrew/jclazz/apps/tester/tests/clazz/ClazzEnum2$SM_1
49: Class: java.awt.Component
50: Utf8: java/awt/Component$BaselineResizeBehavior
51: Utf8: CONSTANT_ASCENT
52: Utf8: switchMap
53: Utf8: [I
54: Utf8: ordinal
55: Utf8: ()I
56: Utf8: java/lang/System
57: Utf8: out
58: Utf8: Ljava/io/PrintStream;
59: Utf8: java/io/PrintStream
60: Utf8: println
61: Utf8: (Ljava/lang/String;)V
62: Utf8: java/awt/Component
