This Class  : ru.andrew.jclazz.apps.tester.tests.clazz.ClazzEnum4
Super Class : java.lang.Enum
Implemented Interfaces:

Version: 50.0
JVM supported: 1.6 and greater

Access Flags: 16433 ( PUBLIC  FINAL  SUPER  ENUM )

Attributes:
@Signature: Ljava/lang/Enum<Lru/andrew/jclazz/apps/tester/tests/clazz/ClazzEnum4;>;
@SourceFile: ClazzEnum4.java

Fields:
E1 : ru.andrew.jclazz.apps.tester.tests.clazz.ClazzEnum4
{
    Access Flags: 16409 ( PUBLIC  STATIC  FINAL  ENUM )

    Attributes:
}

E2 : ru.andrew.jclazz.apps.tester.tests.clazz.ClazzEnum4
{
    Access Flags: 16409 ( PUBLIC  STATIC  FINAL  ENUM )

    Attributes:
}

E3 : ru.andrew.jclazz.apps.tester.tests.clazz.ClazzEnum4
{
    Access Flags: 16409 ( PUBLIC  STATIC  FINAL  ENUM )

    Attributes:
}

str : java.util.List
{
    Access Flags: 2 ( PRIVATE )

    Attributes:
        @Signature: Ljava/util/List<Ljava/lang/String;>;
}

$VALUES : ru.andrew.jclazz.apps.tester.tests.clazz.ClazzEnum4[]
{
    Access Flags: 4122 ( PRIVATE  STATIC  FINAL  SYNTHETIC )

    Attributes:
}


Methods:
values : () : ru.andrew.jclazz.apps.tester.tests.clazz.ClazzEnum4[]
{
    Access Flags: 9 ( PUBLIC  STATIC )

    Attributes:
    CODE
       (
        Max stack = 1
        Max locals = 0
        Attributes:
            @LineNumberTable:
                0: line 5
        Exceptions:
       )
    {
        0 getstatic ru.andrew.jclazz.apps.tester.tests.clazz.ClazzEnum4.$VALUES
        3 invokevirtual clone
        6 checkcast ru.andrew.jclazz.apps.tester.tests.clazz.ClazzEnum4[]
        9 areturn
    }
}

valueOf : (java.lang.String) : ru.andrew.jclazz.apps.tester.tests.clazz.ClazzEnum4
{
    Access Flags: 9 ( PUBLIC  STATIC )

    Attributes:
    CODE
       (
        Max stack = 2
        Max locals = 1
        Attributes:
            @LineNumberTable:
                0: line 5
            @LocalVariableTable: 
                0+11: name (Ljava/lang/String;), 0
        Exceptions:
       )
    {
        0 ldc_w ru.andrew.jclazz.apps.tester.tests.clazz.ClazzEnum4.class (java.lang.Class)
        3 aload_0
        4 invokestatic java.lang.Enum.valueOf
        7 checkcast ru.andrew.jclazz.apps.tester.tests.clazz.ClazzEnum4
        10 areturn
    }
}

<init> : (java.lang.String, int, java.util.List) : void
{
    Access Flags: 2 ( PRIVATE )

    Attributes:
    @Signature: (Ljava/util/List<Ljava/lang/String;>;)V
    CODE
       (
        Max stack = 3
        Max locals = 4
        Attributes:
            @LineNumberTable:
                0: line 11
                6: line 12
                11: line 13
                19: line 14
            @LocalVariableTable: 
                0+20: this (Lru/andrew/jclazz/apps/tester/tests/clazz/ClazzEnum4;), 0
                0+20: str (Ljava/util/List;), 3
            @LocalVariableTypeTable: 
                0+20: str (sign=Ljava/util/List<Ljava/lang/String;>;), 3
        Exceptions:
       )
    {
        0 aload_0
        1 aload_1
        2 iload_2
        3 invokespecial <init>
        6 aload_0
        7 aload_3
        8 putfield str
        11 getstatic java.lang.System.out
        14 ldc "STR" (java.lang.String)
        16 invokevirtual println
        19 return
    }
}

<clinit> : () : void
{
    Access Flags: 8 ( STATIC )

    Attributes:
    CODE
       (
        Max stack = 7
        Max locals = 0
        Attributes:
            @LineNumberTable:
                0: line 7
                63: line 5
                88: line 18
                96: line 19
        Exceptions:
       )
    {
        0 new ru.andrew.jclazz.apps.tester.tests.clazz.ClazzEnum4
        3 dup
        4 ldc "E1" (java.lang.String)
        6 iconst_0
        7 new java.util.ArrayList
        10 dup
        11 iconst_1
        12 invokespecial <init>
        15 invokespecial <init>
        18 putstatic ru.andrew.jclazz.apps.tester.tests.clazz.ClazzEnum4.E1
        21 new ru.andrew.jclazz.apps.tester.tests.clazz.ClazzEnum4
        24 dup
        25 ldc "E2" (java.lang.String)
        27 iconst_1
        28 new java.util.ArrayList
        31 dup
        32 iconst_2
        33 invokespecial <init>
        36 invokespecial <init>
        39 putstatic ru.andrew.jclazz.apps.tester.tests.clazz.ClazzEnum4.E2
        42 new ru.andrew.jclazz.apps.tester.tests.clazz.ClazzEnum4
        45 dup
        46 ldc "E3" (java.lang.String)
        48 iconst_2
        49 new java.util.ArrayList
        52 dup
        53 iconst_3
        54 invokespecial <init>
        57 invokespecial <init>
        60 putstatic ru.andrew.jclazz.apps.tester.tests.clazz.ClazzEnum4.E3
        63 iconst_3
        64 anewarray of ru.andrew.jclazz.apps.tester.tests.clazz.ClazzEnum4
        67 dup
        68 iconst_0
        69 getstatic ru.andrew.jclazz.apps.tester.tests.clazz.ClazzEnum4.E1
        72 aastore
        73 dup
        74 iconst_1
        75 getstatic ru.andrew.jclazz.apps.tester.tests.clazz.ClazzEnum4.E2
        78 aastore
        79 dup
        80 iconst_2
        81 getstatic ru.andrew.jclazz.apps.tester.tests.clazz.ClazzEnum4.E3
        84 aastore
        85 putstatic ru.andrew.jclazz.apps.tester.tests.clazz.ClazzEnum4.$VALUES
        88 getstatic java.lang.System.out
        91 ldc "STATIC" (java.lang.String)
        93 invokevirtual println
        96 return
    }
}

Constant Pool:
0: 
1: Fieldref: ru.andrew.jclazz.apps.tester.tests.clazz.ClazzEnum4[]
2: Methodref: ru.andrew.jclazz.apps.tester.tests.clazz.ClazzEnum4[].clone (()Ljava/lang/Object;)
3: Class: ru.andrew.jclazz.apps.tester.tests.clazz.ClazzEnum4[]
4: Class: ru.andrew.jclazz.apps.tester.tests.clazz.ClazzEnum4
5: Methodref: java.lang.Enum.valueOf ((Ljava/lang/Class;Ljava/lang/String;)Ljava/lang/Enum;)
6: Methodref: java.lang.Enum.<init> ((Ljava/lang/String;I)V)
7: Fieldref: java.util.List
8: Fieldref: java.io.PrintStream
9: String: "STR"
10: Methodref: java.io.PrintStream.println ((Ljava/lang/String;)V)
11: String: "E1"
12: Class: java.util.ArrayList
13: Methodref: java.util.ArrayList.<init> ((I)V)
14: Methodref: ru.andrew.jclazz.apps.tester.tests.clazz.ClazzEnum4.<init> ((Ljava/lang/String;ILjava/util/List;)V)
15: Fieldref: ru.andrew.jclazz.apps.tester.tests.clazz.ClazzEnum4
16: String: "E2"
17: Fieldref: ru.andrew.jclazz.apps.tester.tests.clazz.ClazzEnum4
18: String: "E3"
19: Fieldref: ru.andrew.jclazz.apps.tester.tests.clazz.ClazzEnum4
20: String: "STATIC"
21: Class: java.lang.Enum
22: Utf8: E1
23: Utf8: Lru/andrew/jclazz/apps/tester/tests/clazz/ClazzEnum4;
24: Utf8: E2
25: Utf8: E3
26: Utf8: str
27: Utf8: Ljava/util/List;
28: Utf8: Signature
29: Utf8: Ljava/util/List<Ljava/lang/String;>;
30: Utf8: $VALUES
31: Utf8: [Lru/andrew/jclazz/apps/tester/tests/clazz/ClazzEnum4;
32: Utf8: values
33: Utf8: ()[Lru/andrew/jclazz/apps/tester/tests/clazz/ClazzEnum4;
34: Utf8: Code
35: Utf8: LineNumberTable
36: Utf8: valueOf
37: Utf8: (Ljava/lang/String;)Lru/andrew/jclazz/apps/tester/tests/clazz/ClazzEnum4;
38: Utf8: LocalVariableTable
39: Utf8: name
40: Utf8: Ljava/lang/String;
41: Utf8: <init>
42: Utf8: (Ljava/lang/String;ILjava/util/List;)V
43: Utf8: this
44: Utf8: LocalVariableTypeTable
45: Utf8: (Ljava/util/List<Ljava/lang/String;>;)V
46: Utf8: <clinit>
47: Utf8: ()V
48: Utf8: Ljava/lang/Enum<Lru/andrew/jclazz/apps/tester/tests/clazz/ClazzEnum4;>;
49: Utf8: SourceFile
50: Utf8: ClazzEnum4.java
51: NameAndType: $VALUES ([Lru/andrew/jclazz/apps/tester/tests/clazz/ClazzEnum4;)
52: Class: ru.andrew.jclazz.apps.tester.tests.clazz.ClazzEnum4[]
53: NameAndType: clone (()Ljava/lang/Object;)
54: Utf8: ru/andrew/jclazz/apps/tester/tests/clazz/ClazzEnum4
55: NameAndType: valueOf ((Ljava/lang/Class;Ljava/lang/String;)Ljava/lang/Enum;)
56: NameAndType: <init> ((Ljava/lang/String;I)V)
57: NameAndType: str (Ljava/util/List;)
58: Class: java.lang.System
59: NameAndType: out (Ljava/io/PrintStream;)
60: Utf8: STR
61: Class: java.io.PrintStream
62: NameAndType: println ((Ljava/lang/String;)V)
63: Utf8: java/util/ArrayList
64: NameAndType: <init> ((I)V)
65: NameAndType: <init> ((Ljava/lang/String;ILjava/util/List;)V)
66: NameAndType: E1 (Lru/andrew/jclazz/apps/tester/tests/clazz/ClazzEnum4;)
67: NameAndType: E2 (Lru/andrew/jclazz/apps/tester/tests/clazz/ClazzEnum4;)
68: NameAndType: E3 (Lru/andrew/jclazz/apps/tester/tests/clazz/ClazzEnum4;)
69: Utf8: STATIC
70: Utf8: java/lang/Enum
71: Utf8: clone
72: Utf8: ()Ljava/lang/Object;
73: Utf8: (Ljava/lang/Class;Ljava/lang/String;)Ljava/lang/Enum;
74: Utf8: (Ljava/lang/String;I)V
75: Utf8: java/lang/System
76: Utf8: out
77: Utf8: Ljava/io/PrintStream;
78: Utf8: java/io/PrintStream
79: Utf8: println
80: Utf8: (Ljava/lang/String;)V
81: Utf8: (I)V
