This Class  : ru.andrew.jclazz.apps.tester.tests.other.Fibo
Super Class : java.lang.Object
Implemented Interfaces:

Version: 50.0
JVM supported: 1.6 and greater

Access Flags: 32 ( SUPER )

Attributes:
@SourceFile: Fibo.java

Fields:

Methods:
<init> : () : void
{
    Access Flags: 0 ()

    Attributes:
    CODE
       (
        Max stack = 1
        Max locals = 1
        Attributes:
            @LineNumberTable:
                0: line 7
                4: line 8
            @LocalVariableTable: 
                0+5: this (Lru/andrew/jclazz/apps/tester/tests/other/Fibo;), 0
        Exceptions:
       )
    {
        0 aload_0
        1 invokespecial <init>
        4 return
    }
}

fib : (int) : int
{
    Access Flags: 10 ( PRIVATE  STATIC )

    Attributes:
    CODE
       (
        Max stack = 3
        Max locals = 1
        Attributes:
            @LineNumberTable:
                0: line 12
                5: line 14
                19: line 16
            @LocalVariableTable: 
                0+21: x (I), 0
            @StackMapTable: 
                SameFrame (+19): 
            
        Exceptions:
       )
    {
        0 iload_0
        1 iconst_1
        2 if_icmple 19
        5 iload_0
        6 iconst_1
        7 isub
        8 invokestatic ru.andrew.jclazz.apps.tester.tests.other.Fibo.fib
        11 iload_0
        12 iconst_2
        13 isub
        14 invokestatic ru.andrew.jclazz.apps.tester.tests.other.Fibo.fib
        17 iadd
        18 ireturn
        19 iload_0
        20 ireturn
    }
}

main : (java.lang.String[]) : void
{
    Access Flags: 9 ( PUBLIC  STATIC )

    Attributes:
    @Exceptions: 
            java.lang.Exception
    CODE
       (
        Max stack = 3
        Max locals = 3
        Attributes:
            @LineNumberTable:
                0: line 21
                2: line 24
                9: line 30
                12: line 26
                13: line 28
                21: line 29
                25: line 31
                30: line 32
                64: line 33
            @LocalVariableTable: 
                13+12: e (Ljava/lang/Exception;), 2
                0+65: args ([Ljava/lang/String;), 0
                2+63: number (I), 1
                30+35: value (I), 2
            @StackMapTable: 
                FullFrame (+12): locals - Object(java.lang.String[]) Integer, stack - Object(java.lang.Exception)
                SameFrame (+12): 
            
        Exceptions:
            [2-9): 12 - java.lang.Exception
       )
    {
        0 iconst_0
        1 istore_1
        2 aload_0
        3 iconst_0
        4 aaload
        5 invokestatic java.lang.Integer.parseInt
        8 istore_1
        9 goto 25
        12 astore_2
        13 getstatic java.lang.System.out
        16 ldc "Input error" (java.lang.String)
        18 invokevirtual println
        21 iconst_1
        22 invokestatic java.lang.System.exit
        25 iload_1
        26 invokestatic ru.andrew.jclazz.apps.tester.tests.other.Fibo.fib
        29 istore_2
        30 getstatic java.lang.System.out
        33 new java.lang.StringBuilder
        36 dup
        37 invokespecial <init>
        40 ldc "fibonacci(" (java.lang.String)
        42 invokevirtual append
        45 iload_1
        46 invokevirtual append
        49 ldc ") = " (java.lang.String)
        51 invokevirtual append
        54 iload_2
        55 invokevirtual append
        58 invokevirtual toString
        61 invokevirtual println
        64 return
    }
}

Constant Pool:
0: 
1: Methodref: java.lang.Object.<init> (()V)
2: Methodref: ru.andrew.jclazz.apps.tester.tests.other.Fibo.fib ((I)I)
3: Methodref: java.lang.Integer.parseInt ((Ljava/lang/String;)I)
4: Class: java.lang.Exception
5: Fieldref: java.io.PrintStream
6: String: "Input error"
7: Methodref: java.io.PrintStream.println ((Ljava/lang/String;)V)
8: Methodref: java.lang.System.exit ((I)V)
9: Class: java.lang.StringBuilder
10: Methodref: java.lang.StringBuilder.<init> (()V)
11: String: "fibonacci("
12: Methodref: java.lang.StringBuilder.append ((Ljava/lang/String;)Ljava/lang/StringBuilder;)
13: Methodref: java.lang.StringBuilder.append ((I)Ljava/lang/StringBuilder;)
14: String: ") = "
15: Methodref: java.lang.StringBuilder.toString (()Ljava/lang/String;)
16: Class: ru.andrew.jclazz.apps.tester.tests.other.Fibo
17: Class: java.lang.Object
18: Utf8: <init>
19: Utf8: ()V
20: Utf8: Code
21: Utf8: LineNumberTable
22: Utf8: LocalVariableTable
23: Utf8: this
24: Utf8: Lru/andrew/jclazz/apps/tester/tests/other/Fibo;
25: Utf8: fib
26: Utf8: (I)I
27: Utf8: x
28: Utf8: I
29: Utf8: StackMapTable
30: Utf8: main
31: Utf8: ([Ljava/lang/String;)V
32: Utf8: e
33: Utf8: Ljava/lang/Exception;
34: Utf8: args
35: Utf8: [Ljava/lang/String;
36: Utf8: number
37: Utf8: value
38: Class: java.lang.String[]
39: Class: java.lang.Exception
40: Utf8: Exceptions
41: Utf8: SourceFile
42: Utf8: Fibo.java
43: NameAndType: <init> (()V)
44: NameAndType: fib ((I)I)
45: Class: java.lang.Integer
46: NameAndType: parseInt ((Ljava/lang/String;)I)
47: Utf8: java/lang/Exception
48: Class: java.lang.System
49: NameAndType: out (Ljava/io/PrintStream;)
50: Utf8: Input error
51: Class: java.io.PrintStream
52: NameAndType: println ((Ljava/lang/String;)V)
53: NameAndType: exit ((I)V)
54: Utf8: java/lang/StringBuilder
55: Utf8: fibonacci(
56: NameAndType: append ((Ljava/lang/String;)Ljava/lang/StringBuilder;)
57: NameAndType: append ((I)Ljava/lang/StringBuilder;)
58: Utf8: ) = 
59: NameAndType: toString (()Ljava/lang/String;)
60: Utf8: ru/andrew/jclazz/apps/tester/tests/other/Fibo
61: Utf8: java/lang/Object
62: Utf8: java/lang/Integer
63: Utf8: parseInt
64: Utf8: (Ljava/lang/String;)I
65: Utf8: java/lang/System
66: Utf8: out
67: Utf8: Ljava/io/PrintStream;
68: Utf8: java/io/PrintStream
69: Utf8: println
70: Utf8: (Ljava/lang/String;)V
71: Utf8: exit
72: Utf8: (I)V
73: Utf8: append
74: Utf8: (Ljava/lang/String;)Ljava/lang/StringBuilder;
75: Utf8: (I)Ljava/lang/StringBuilder;
76: Utf8: toString
77: Utf8: ()Ljava/lang/String;
