This Class  : ru.andrew.jclazz.apps.tester.tests.composite.FinalParam
Super Class : java.lang.Object
Implemented Interfaces:

Version: 46.0
JVM supported: 1.2 and greater

Access Flags: 33 ( PUBLIC  SUPER )

Attributes:
@SourceFile: FinalParam.java
@InnerClasses: 
    * Inner class - ru.andrew.jclazz.apps.tester.tests.composite.FinalParam$1
      Outer class - 
      Inner name - 
      Inner class access flags - 0
    * Inner class - ru.andrew.jclazz.apps.tester.tests.composite.FinalParam$2
      Outer class - 
      Inner name - 
      Inner class access flags - 0

Fields:

Methods:
<init> : () : void
{
    Access Flags: 1 ( PUBLIC )

    Attributes:
    CODE
       (
        Max stack = 1
        Max locals = 1
        Attributes:
            @LineNumberTable:
                0: line 9
                4: line 10
            @LocalVariableTable: 
                0+5: this (Lru/andrew/jclazz/apps/tester/tests/composite/FinalParam;), 0
        Exceptions:
       )
    {
        0 aload_0
        1 invokespecial <init>
        4 return
    }
}

test1 : (java.lang.String, java.lang.String) : void
{
    Access Flags: 1 ( PUBLIC )

    Attributes:
    CODE
       (
        Max stack = 4
        Max locals = 4
        Attributes:
            @LineNumberTable:
                0: line 14
                10: line 24
            @LocalVariableTable: 
                0+11: this (Lru/andrew/jclazz/apps/tester/tests/composite/FinalParam;), 0
                0+11: s0 (Ljava/lang/String;), 1
                0+11: str (Ljava/lang/String;), 2
                10+1: comp (Ljava/util/Comparator;), 3
        Exceptions:
       )
    {
        0 new ru.andrew.jclazz.apps.tester.tests.composite.FinalParam$1
        3 dup
        4 aload_0
        5 aload_2
        6 invokespecial <init>
        9 astore_3
        10 return
    }
}

test2 : (java.lang.String) : void
{
    Access Flags: 1 ( PUBLIC )

    Attributes:
    CODE
       (
        Max stack = 4
        Max locals = 4
        Attributes:
            @LineNumberTable:
                0: line 28
                2: line 29
                12: line 39
                19: line 40
            @LocalVariableTable: 
                0+20: this (Lru/andrew/jclazz/apps/tester/tests/composite/FinalParam;), 0
                0+20: s0 (Ljava/lang/String;), 1
                2+18: str (Ljava/lang/String;), 2
                12+8: comp (Ljava/util/Comparator;), 3
        Exceptions:
       )
    {
        0 aload_1
        1 astore_2
        2 new ru.andrew.jclazz.apps.tester.tests.composite.FinalParam$2
        5 dup
        6 aload_0
        7 aload_2
        8 invokespecial <init>
        11 astore_3
        12 getstatic java.lang.System.out
        15 aload_2
        16 invokevirtual println
        19 return
    }
}

Constant Pool:
0: 
1: Methodref: java.lang.Object.<init> (()V)
2: Class: ru.andrew.jclazz.apps.tester.tests.composite.FinalParam$1
3: Methodref: ru.andrew.jclazz.apps.tester.tests.composite.FinalParam$1.<init> ((Lru/andrew/jclazz/apps/tester/tests/composite/FinalParam;Ljava/lang/String;)V)
4: Class: ru.andrew.jclazz.apps.tester.tests.composite.FinalParam$2
5: Methodref: ru.andrew.jclazz.apps.tester.tests.composite.FinalParam$2.<init> ((Lru/andrew/jclazz/apps/tester/tests/composite/FinalParam;Ljava/lang/String;)V)
6: Fieldref: java.io.PrintStream
7: Methodref: java.io.PrintStream.println ((Ljava/lang/String;)V)
8: Class: ru.andrew.jclazz.apps.tester.tests.composite.FinalParam
9: Class: java.lang.Object
10: Utf8: <init>
11: Utf8: ()V
12: Utf8: Code
13: Utf8: LineNumberTable
14: Utf8: LocalVariableTable
15: Utf8: this
16: Utf8: Lru/andrew/jclazz/apps/tester/tests/composite/FinalParam;
17: Utf8: test1
18: Utf8: (Ljava/lang/String;Ljava/lang/String;)V
19: Utf8: s0
20: Utf8: Ljava/lang/String;
21: Utf8: str
22: Utf8: comp
23: Utf8: Ljava/util/Comparator;
24: Utf8: test2
25: Utf8: (Ljava/lang/String;)V
26: Utf8: SourceFile
27: Utf8: FinalParam.java
28: NameAndType: <init> (()V)
29: Utf8: ru/andrew/jclazz/apps/tester/tests/composite/FinalParam$1
30: Utf8: 
31: Utf8: InnerClasses
32: NameAndType: <init> ((Lru/andrew/jclazz/apps/tester/tests/composite/FinalParam;Ljava/lang/String;)V)
33: Utf8: ru/andrew/jclazz/apps/tester/tests/composite/FinalParam$2
34: Class: java.lang.System
35: NameAndType: out (Ljava/io/PrintStream;)
36: Class: java.io.PrintStream
37: NameAndType: println ((Ljava/lang/String;)V)
38: Utf8: ru/andrew/jclazz/apps/tester/tests/composite/FinalParam
39: Utf8: java/lang/Object
40: Utf8: (Lru/andrew/jclazz/apps/tester/tests/composite/FinalParam;Ljava/lang/String;)V
41: Utf8: java/lang/System
42: Utf8: out
43: Utf8: Ljava/io/PrintStream;
44: Utf8: java/io/PrintStream
45: Utf8: println
