This Class  : ru.andrew.jclazz.apps.tester.tests.composite.DoubleIfInLoop
Super Class : java.lang.Object
Implemented Interfaces:

Version: 50.0
JVM supported: 1.6 and greater

Access Flags: 33 ( PUBLIC  SUPER )

Attributes:
@SourceFile: DoubleIfInLoop.java

Fields:
exit : boolean
{
    Access Flags: 1 ( PUBLIC )

    Attributes:
}


Methods:
<init> : () : void
{
    Access Flags: 1 ( PUBLIC )

    Attributes:
    CODE
       (
        Max stack = 1
        Max locals = 1
        Attributes:
            @LineNumberTable:
                0: line 8
                4: line 9
            @LocalVariableTable: 
                0+5: this (Lru/andrew/jclazz/apps/tester/tests/composite/DoubleIfInLoop;), 0
        Exceptions:
       )
    {
        0 aload_0
        1 invokespecial <init>
        4 return
    }
}

run : (java.lang.String, java.lang.String) : void
{
    Access Flags: 1 ( PUBLIC )

    Attributes:
    CODE
       (
        Max stack = 2
        Max locals = 3
        Attributes:
            @LineNumberTable:
                0: line 13
                7: line 15
                15: line 16
                24: line 18
                33: line 20
                41: line 21
                48: line 25
                56: line 28
                65: line 30
                73: line 31
                77: line 33
                88: line 35
            @LocalVariableTable: 
                0+89: this (Lru/andrew/jclazz/apps/tester/tests/composite/DoubleIfInLoop;), 0
                0+89: cmdS (Ljava/lang/String;), 1
                0+89: messageS (Ljava/lang/String;), 2
            @StackMapTable: 
                SameFrame (+0): 
                SameFrame (+47): 
                SameFrame (+7): 
                SameFrame (+20): 
                SameFrame (+10): 
            
        Exceptions:
       )
    {
        0 aload_0
        1 getfield exit
        4 ifeq 88
        7 getstatic java.lang.System.out
        10 ldc "LOOP START" (java.lang.String)
        12 invokevirtual println
        15 aload_1
        16 ldc "connect" (java.lang.String)
        18 invokevirtual equalsIgnoreCase
        21 ifeq 56
        24 aload_2
        25 ldc "accept" (java.lang.String)
        27 invokevirtual equalsIgnoreCase
        30 ifne 48
        33 getstatic java.lang.System.out
        36 ldc "IF-1-1" (java.lang.String)
        38 invokevirtual println
        41 iconst_1
        42 invokestatic java.lang.System.exit
        45 goto 56
        48 getstatic java.lang.System.out
        51 ldc "IF-1-2" (java.lang.String)
        53 invokevirtual println
        56 aload_1
        57 ldc "disconnect" (java.lang.String)
        59 invokevirtual equalsIgnoreCase
        62 ifeq 77
        65 getstatic java.lang.System.out
        68 ldc "IF-2-1" (java.lang.String)
        70 invokevirtual println
        73 iconst_1
        74 invokestatic java.lang.System.exit
        77 getstatic java.lang.System.out
        80 ldc "LOOP END" (java.lang.String)
        82 invokevirtual println
        85 goto 0
        88 return
    }
}

Constant Pool:
0: 
1: Methodref: java.lang.Object.<init> (()V)
2: Fieldref: boolean
3: Fieldref: java.io.PrintStream
4: String: "LOOP START"
5: Methodref: java.io.PrintStream.println ((Ljava/lang/String;)V)
6: String: "connect"
7: Methodref: java.lang.String.equalsIgnoreCase ((Ljava/lang/String;)Z)
8: String: "accept"
9: String: "IF-1-1"
10: Methodref: java.lang.System.exit ((I)V)
11: String: "IF-1-2"
12: String: "disconnect"
13: String: "IF-2-1"
14: String: "LOOP END"
15: Class: ru.andrew.jclazz.apps.tester.tests.composite.DoubleIfInLoop
16: Class: java.lang.Object
17: Utf8: exit
18: Utf8: Z
19: Utf8: <init>
20: Utf8: ()V
21: Utf8: Code
22: Utf8: LineNumberTable
23: Utf8: LocalVariableTable
24: Utf8: this
25: Utf8: Lru/andrew/jclazz/apps/tester/tests/composite/DoubleIfInLoop;
26: Utf8: run
27: Utf8: (Ljava/lang/String;Ljava/lang/String;)V
28: Utf8: cmdS
29: Utf8: Ljava/lang/String;
30: Utf8: messageS
31: Utf8: StackMapTable
32: Utf8: SourceFile
33: Utf8: DoubleIfInLoop.java
34: NameAndType: <init> (()V)
35: NameAndType: exit (Z)
36: Class: java.lang.System
37: NameAndType: out (Ljava/io/PrintStream;)
38: Utf8: LOOP START
39: Class: java.io.PrintStream
40: NameAndType: println ((Ljava/lang/String;)V)
41: Utf8: connect
42: Class: java.lang.String
43: NameAndType: equalsIgnoreCase ((Ljava/lang/String;)Z)
44: Utf8: accept
45: Utf8: IF-1-1
46: NameAndType: exit ((I)V)
47: Utf8: IF-1-2
48: Utf8: disconnect
49: Utf8: IF-2-1
50: Utf8: LOOP END
51: Utf8: ru/andrew/jclazz/apps/tester/tests/composite/DoubleIfInLoop
52: Utf8: java/lang/Object
53: Utf8: java/lang/System
54: Utf8: out
55: Utf8: Ljava/io/PrintStream;
56: Utf8: java/io/PrintStream
57: Utf8: println
58: Utf8: (Ljava/lang/String;)V
59: Utf8: java/lang/String
60: Utf8: equalsIgnoreCase
61: Utf8: (Ljava/lang/String;)Z
62: Utf8: (I)V
