This Class  : ru.andrew.jclazz.apps.tester.tests.composite.LVs
Super Class : java.lang.Object
Implemented Interfaces:

Version: 50.0
JVM supported: 1.6 and greater

Access Flags: 33 ( PUBLIC  SUPER )

Attributes:
@SourceFile: LVs.java

Fields:

Methods:
<init> : () : void
{
    Access Flags: 1 ( PUBLIC )

    Attributes:
    CODE
       (
        Max stack = 1
        Max locals = 1
        Attributes:
            @LineNumberTable:
                0: line 10
                4: line 11
            @LocalVariableTable: 
                0+5: this (Lru/andrew/jclazz/apps/tester/tests/composite/LVs;), 0
        Exceptions:
       )
    {
        0 aload_0
        1 invokespecial <init>
        4 return
    }
}

test1 : () : void
{
    Access Flags: 1 ( PUBLIC )

    Attributes:
    CODE
       (
        Max stack = 2
        Max locals = 3
        Attributes:
            @LineNumberTable:
                0: line 15
                2: line 18
                5: line 19
                9: line 24
                12: line 21
                13: line 23
                20: line 25
            @LocalVariableTable: 
                13+7: e (Ljava/lang/Exception;), 2
                0+21: this (Lru/andrew/jclazz/apps/tester/tests/composite/LVs;), 0
                2+19: i (I), 1
            @StackMapTable: 
                FullFrame (+12): locals - Object(ru.andrew.jclazz.apps.tester.tests.composite.LVs) Integer, stack - Object(java.lang.Exception)
                SameFrame (+7): 
            
        Exceptions:
            [2-9): 12 - java.lang.Exception
       )
    {
        0 iconst_0
        1 istore_1
        2 bipush 7 (int)
        4 istore_1
        5 iload_1
        6 iconst_4
        7 iand
        8 istore_1
        9 goto 20
        12 astore_2
        13 getstatic java.lang.System.out
        16 aload_2
        17 invokevirtual println
        20 return
    }
}

test2 : (int) : void
{
    Access Flags: 1 ( PUBLIC )

    Attributes:
    CODE
       (
        Max stack = 2
        Max locals = 3
        Attributes:
            @LineNumberTable:
                0: line 29
                2: line 32
                5: line 33
                9: line 38
                12: line 35
                13: line 37
                20: line 39
            @LocalVariableTable: 
                13+7: e (Ljava/lang/Exception;), 2
                0+21: this (Lru/andrew/jclazz/apps/tester/tests/composite/LVs;), 0
                0+21: i (I), 1
            @StackMapTable: 
                SameLocals1StackItemFrame (+12): stack item = Object(java.lang.Exception)
                SameFrame (+7): 
            
        Exceptions:
            [2-9): 12 - java.lang.Exception
       )
    {
        0 iconst_0
        1 istore_1
        2 bipush 7 (int)
        4 istore_1
        5 iload_1
        6 iconst_4
        7 iand
        8 istore_1
        9 goto 20
        12 astore_2
        13 getstatic java.lang.System.out
        16 aload_2
        17 invokevirtual println
        20 return
    }
}

test3 : () : java.lang.String
{
    Access Flags: 1 ( PUBLIC )

    Attributes:
    CODE
       (
        Max stack = 2
        Max locals = 3
        Attributes:
            @LineNumberTable:
                0: line 43
                2: line 46
                5: line 51
                8: line 48
                9: line 50
                17: line 52
            @LocalVariableTable: 
                9+8: e (Ljava/lang/Exception;), 2
                0+19: this (Lru/andrew/jclazz/apps/tester/tests/composite/LVs;), 0
                2+17: str (Ljava/lang/String;), 1
            @StackMapTable: 
                FullFrame (+8): locals - Object(ru.andrew.jclazz.apps.tester.tests.composite.LVs) Object(java.lang.String), stack - Object(java.lang.Exception)
                SameFrame (+8): 
            
        Exceptions:
            [2-5): 8 - java.lang.Exception
       )
    {
        0 aconst_null
        1 astore_1
        2 ldc "123" (java.lang.String)
        4 astore_1
        5 goto 17
        8 astore_2
        9 getstatic java.lang.System.out
        12 ldc "EXCEPTION" (java.lang.String)
        14 invokevirtual println
        17 aload_1
        18 areturn
    }
}

test4 : () : void
{
    Access Flags: 1 ( PUBLIC )

    Attributes:
    CODE
       (
        Max stack = 3
        Max locals = 3
        Attributes:
            @LineNumberTable:
                0: line 57
                8: line 58
                10: line 59
                17: line 61
                25: line 62
                33: line 63
                58: line 64
                66: line 66
            @LocalVariableTable: 
                0+67: this (Lru/andrew/jclazz/apps/tester/tests/composite/LVs;), 0
                8+59: list (Ljava/util/HashSet;), 1
                10+57: i (C), 2
            @StackMapTable: 
                AppendFrame (+10): additional locals - Object(java.util.HashSet) Integer
                SameFrame (+55): 
            
        Exceptions:
       )
    {
        0 new java.util.HashSet
        3 dup
        4 invokespecial <init>
        7 astore_1
        8 iconst_0
        9 istore_2
        10 iload_2
        11 sipush 150 (int)
        14 if_icmpge 66
        17 getstatic java.lang.System.out
        20 ldc "CYCLE" (java.lang.String)
        22 invokevirtual println
        25 new java.util.LinkedHashSet
        28 dup
        29 invokespecial <init>
        32 astore_1
        33 getstatic java.lang.System.out
        36 new java.lang.StringBuilder
        39 dup
        40 invokespecial <init>
        43 ldc "i = " (java.lang.String)
        45 invokevirtual append
        48 iload_2
        49 invokevirtual append
        52 invokevirtual toString
        55 invokevirtual println
        58 iload_2
        59 iconst_1
        60 iadd
        61 i2c
        62 istore_2
        63 goto 10
        66 return
    }
}

test5 : () : void
{
    Access Flags: 1 ( PUBLIC )

    Attributes:
    @Exceptions: 
            java.io.IOException
    CODE
       (
        Max stack = 7
        Max locals = 3
        Attributes:
            @LineNumberTable:
                0: line 70
                24: line 71
                26: line 72
                40: line 74
                68: line 76
            @LocalVariableTable: 
                0+69: this (Lru/andrew/jclazz/apps/tester/tests/composite/LVs;), 0
                24+45: br (Ljava/io/BufferedReader;), 1
                26+43: s (Ljava/lang/String;), 2
            @StackMapTable: 
                AppendFrame (+26): additional locals - Object(java.io.BufferedReader) Object(java.lang.String)
                SameFrame (+41): 
            
        Exceptions:
       )
    {
        0 new java.io.BufferedReader
        3 dup
        4 new java.io.InputStreamReader
        7 dup
        8 new java.io.FileInputStream
        11 dup
        12 ldc "path" (java.lang.String)
        14 invokespecial <init>
        17 invokespecial <init>
        20 invokespecial <init>
        23 astore_1
        24 aconst_null
        25 astore_2
        26 aload_1
        27 invokevirtual readLine
        30 dup
        31 astore_2
        32 ldc "456" (java.lang.String)
        34 invokevirtual equals
        37 ifeq 68
        40 getstatic java.lang.System.out
        43 new java.lang.StringBuilder
        46 dup
        47 invokespecial <init>
        50 ldc " = " (java.lang.String)
        52 invokevirtual append
        55 aload_2
        56 invokevirtual append
        59 invokevirtual toString
        62 invokevirtual println
        65 goto 26
        68 return
    }
}

test6 : (boolean) : void
{
    Access Flags: 1 ( PUBLIC )

    Attributes:
    @Exceptions: 
            java.io.IOException
    CODE
       (
        Max stack = 3
        Max locals = 3
        Attributes:
            @LineNumberTable:
                0: line 80
                2: line 81
                23: line 83
                51: line 85
            @LocalVariableTable: 
                0+52: this (Lru/andrew/jclazz/apps/tester/tests/composite/LVs;), 0
                0+52: test (Z), 1
                2+50: file (Ljava/io/File;), 2
            @StackMapTable: 
                AppendFrame (+2): additional locals - Object(java.io.File)
                SameFrame (+48): 
            
        Exceptions:
       )
    {
        0 aconst_null
        1 astore_2
        2 iload_1
        3 ifeq 51
        6 new java.io.File
        9 dup
        10 ldc "path" (java.lang.String)
        12 invokespecial <init>
        15 dup
        16 astore_2
        17 invokevirtual isDirectory
        20 ifeq 51
        23 getstatic java.lang.System.out
        26 new java.lang.StringBuilder
        29 dup
        30 invokespecial <init>
        33 ldc " = " (java.lang.String)
        35 invokevirtual append
        38 aload_2
        39 invokevirtual append
        42 invokevirtual toString
        45 invokevirtual println
        48 goto 2
        51 return
    }
}

test7 : (boolean) : void
{
    Access Flags: 1 ( PUBLIC )

    Attributes:
    @Exceptions: 
            java.io.IOException
    CODE
       (
        Max stack = 3
        Max locals = 3
        Attributes:
            @LineNumberTable:
                0: line 89
                2: line 90
                25: line 92
                53: line 94
            @LocalVariableTable: 
                0+54: this (Lru/andrew/jclazz/apps/tester/tests/composite/LVs;), 0
                0+54: test (Z), 1
                2+52: i (I), 2
            @StackMapTable: 
                AppendFrame (+2): additional locals - Integer
                SameFrame (+50): 
            
        Exceptions:
       )
    {
        0 iconst_0
        1 istore_2
        2 iload_1
        3 ifeq 53
        6 new java.lang.Integer
        9 dup
        10 ldc "123" (java.lang.String)
        12 invokespecial <init>
        15 invokevirtual intValue
        18 dup
        19 istore_2
        20 bipush 10 (int)
        22 if_icmple 53
        25 getstatic java.lang.System.out
        28 new java.lang.StringBuilder
        31 dup
        32 invokespecial <init>
        35 ldc " = " (java.lang.String)
        37 invokevirtual append
        40 iload_2
        41 invokevirtual append
        44 invokevirtual toString
        47 invokevirtual println
        50 goto 2
        53 return
    }
}

test8 : (java.lang.String, char, int) : void
{
    Access Flags: 1 ( PUBLIC )

    Attributes:
    CODE
       (
        Max stack = 2
        Max locals = 4
        Attributes:
            @LineNumberTable:
                0: line 98
                6: line 100
                14: line 102
            @LocalVariableTable: 
                0+15: this (Lru/andrew/jclazz/apps/tester/tests/composite/LVs;), 0
                0+15: sender (Ljava/lang/String;), 1
                0+15: keyCode (C), 2
                0+15: modifiers (I), 3
            @StackMapTable: 
                SameFrame (+14): 
            
        Exceptions:
       )
    {
        0 bipush 106 (int)
        2 iload_2
        3 if_icmpne 14
        6 getstatic java.lang.System.out
        9 ldc "IF char" (java.lang.String)
        11 invokevirtual println
        14 return
    }
}

Constant Pool:
0: 
1: Methodref: java.lang.Object.<init> (()V)
2: Class: java.lang.Exception
3: Fieldref: java.io.PrintStream
4: Methodref: java.io.PrintStream.println ((Ljava/lang/Object;)V)
5: String: "123"
6: String: "EXCEPTION"
7: Methodref: java.io.PrintStream.println ((Ljava/lang/String;)V)
8: Class: java.util.HashSet
9: Methodref: java.util.HashSet.<init> (()V)
10: String: "CYCLE"
11: Class: java.util.LinkedHashSet
12: Methodref: java.util.LinkedHashSet.<init> (()V)
13: Class: java.lang.StringBuilder
14: Methodref: java.lang.StringBuilder.<init> (()V)
15: String: "i = "
16: Methodref: java.lang.StringBuilder.append ((Ljava/lang/String;)Ljava/lang/StringBuilder;)
17: Methodref: java.lang.StringBuilder.append ((C)Ljava/lang/StringBuilder;)
18: Methodref: java.lang.StringBuilder.toString (()Ljava/lang/String;)
19: Class: java.io.BufferedReader
20: Class: java.io.InputStreamReader
21: Class: java.io.FileInputStream
22: String: "path"
23: Methodref: java.io.FileInputStream.<init> ((Ljava/lang/String;)V)
24: Methodref: java.io.InputStreamReader.<init> ((Ljava/io/InputStream;)V)
25: Methodref: java.io.BufferedReader.<init> ((Ljava/io/Reader;)V)
26: Methodref: java.io.BufferedReader.readLine (()Ljava/lang/String;)
27: String: "456"
28: Methodref: java.lang.String.equals ((Ljava/lang/Object;)Z)
29: String: " = "
30: Class: java.io.File
31: Methodref: java.io.File.<init> ((Ljava/lang/String;)V)
32: Methodref: java.io.File.isDirectory (()Z)
33: Methodref: java.lang.StringBuilder.append ((Ljava/lang/Object;)Ljava/lang/StringBuilder;)
34: Class: java.lang.Integer
35: Methodref: java.lang.Integer.<init> ((Ljava/lang/String;)V)
36: Methodref: java.lang.Integer.intValue (()I)
37: Methodref: java.lang.StringBuilder.append ((I)Ljava/lang/StringBuilder;)
38: String: "IF char"
39: Class: ru.andrew.jclazz.apps.tester.tests.composite.LVs
40: Class: java.lang.Object
41: Utf8: <init>
42: Utf8: ()V
43: Utf8: Code
44: Utf8: LineNumberTable
45: Utf8: LocalVariableTable
46: Utf8: this
47: Utf8: Lru/andrew/jclazz/apps/tester/tests/composite/LVs;
48: Utf8: test1
49: Utf8: e
50: Utf8: Ljava/lang/Exception;
51: Utf8: i
52: Utf8: I
53: Utf8: StackMapTable
54: Class: ru.andrew.jclazz.apps.tester.tests.composite.LVs
55: Class: java.lang.Exception
56: Utf8: test2
57: Utf8: (I)V
58: Utf8: test3
59: Utf8: ()Ljava/lang/String;
60: Utf8: str
61: Utf8: Ljava/lang/String;
62: Class: java.lang.String
63: Utf8: test4
64: Utf8: list
65: Utf8: Ljava/util/HashSet;
66: Utf8: C
67: Class: java.util.HashSet
68: Utf8: test5
69: Utf8: br
70: Utf8: Ljava/io/BufferedReader;
71: Utf8: s
72: Class: java.io.BufferedReader
73: Utf8: Exceptions
74: Class: java.io.IOException
75: Utf8: test6
76: Utf8: (Z)V
77: Utf8: test
78: Utf8: Z
79: Utf8: file
80: Utf8: Ljava/io/File;
81: Class: java.io.File
82: Utf8: test7
83: Utf8: test8
84: Utf8: (Ljava/lang/String;CI)V
85: Utf8: sender
86: Utf8: keyCode
87: Utf8: modifiers
88: Utf8: SourceFile
89: Utf8: LVs.java
90: NameAndType: <init> (()V)
91: Utf8: java/lang/Exception
92: Class: java.lang.System
93: NameAndType: out (Ljava/io/PrintStream;)
94: Class: java.io.PrintStream
95: NameAndType: println ((Ljava/lang/Object;)V)
96: Utf8: 123
97: Utf8: EXCEPTION
98: NameAndType: println ((Ljava/lang/String;)V)
99: Utf8: java/util/HashSet
100: Utf8: CYCLE
101: Utf8: java/util/LinkedHashSet
102: Utf8: java/lang/StringBuilder
103: Utf8: i = 
104: NameAndType: append ((Ljava/lang/String;)Ljava/lang/StringBuilder;)
105: NameAndType: append ((C)Ljava/lang/StringBuilder;)
106: NameAndType: toString (()Ljava/lang/String;)
107: Utf8: java/io/BufferedReader
108: Utf8: java/io/InputStreamReader
109: Utf8: java/io/FileInputStream
110: Utf8: path
111: NameAndType: <init> ((Ljava/lang/String;)V)
112: NameAndType: <init> ((Ljava/io/InputStream;)V)
113: NameAndType: <init> ((Ljava/io/Reader;)V)
114: NameAndType: readLine (()Ljava/lang/String;)
115: Utf8: 456
116: Class: java.lang.String
117: NameAndType: equals ((Ljava/lang/Object;)Z)
118: Utf8:  = 
119: Utf8: java/io/File
120: NameAndType: isDirectory (()Z)
121: NameAndType: append ((Ljava/lang/Object;)Ljava/lang/StringBuilder;)
122: Utf8: java/lang/Integer
123: NameAndType: intValue (()I)
124: NameAndType: append ((I)Ljava/lang/StringBuilder;)
125: Utf8: IF char
126: Utf8: ru/andrew/jclazz/apps/tester/tests/composite/LVs
127: Utf8: java/lang/Object
128: Utf8: java/lang/String
129: Utf8: java/io/IOException
130: Utf8: java/lang/System
131: Utf8: out
132: Utf8: Ljava/io/PrintStream;
133: Utf8: java/io/PrintStream
134: Utf8: println
135: Utf8: (Ljava/lang/Object;)V
136: Utf8: (Ljava/lang/String;)V
137: Utf8: append
138: Utf8: (Ljava/lang/String;)Ljava/lang/StringBuilder;
139: Utf8: (C)Ljava/lang/StringBuilder;
140: Utf8: toString
141: Utf8: (Ljava/io/InputStream;)V
142: Utf8: (Ljava/io/Reader;)V
143: Utf8: readLine
144: Utf8: equals
145: Utf8: (Ljava/lang/Object;)Z
146: Utf8: isDirectory
147: Utf8: ()Z
148: Utf8: (Ljava/lang/Object;)Ljava/lang/StringBuilder;
149: Utf8: intValue
150: Utf8: ()I
151: Utf8: (I)Ljava/lang/StringBuilder;
